Workbook

Sheet Data (1)
A1: Source.Name | B1: Column1 | C1: Column2 | D1: Column3 | E1: Column4 | F1: Column5
A2: ABBV_FULL_IS_CF_BS.xlsx | B2: Total Debt | C2: 76684 | D2: 63271 | E2: 59385 | F2: 67144
A3: ABBV_FULL_IS_CF_BS.xlsx | B3: Cash And Cash Equivalents | C3: 9746 | D3: 9201 | E3: 12814 | F3: 5524
A4: AMGN_FULL_IS_CF_BS.xlsx | B4: Total Debt | C4: 33309 | D4: 38945 | E4: 64613 | F4: 60099
A5: AMGN_FULL_IS_CF_BS.xlsx | B5: Cash And Cash Equivalents | C5: 7989 | D5: 7629 | E5: 10944 | F5: 11973
A6: AZN_FULL_IS_CF_BS.xlsx | B6: Total Debt | C6: 30688 | D6: 29143 | E6: 28407 | F6: 30114
A7: AZN_FULL_IS_CF_BS.xlsx | B7: Cash And Cash Equivalents | C7: 6329 | D7: 6166 | E7: 5840 | F7: 5488
A8: BMY_FULL_IS_CF_BS.xlsx | B8: Total Debt | C8: 45596 | D8: 40717 | E8: 41464 | F8: 51200
A9: BMY_FULL_IS_CF_BS.xlsx | B9: Cash And Cash Equivalents | C9: 13979 | D9: 9123 | E9: 11464 | F9: 10346
A10: LLY_FULL_IS_CF_BS.xlsx | B10: Total Debt | C10: 16884.7 | D10: 16238.6 | E10: 25225.3 | F10: 33644.2
A11: LLY_FULL_IS_CF_BS.xlsx | B11: Cash And Cash Equivalents | C11: 3818.5 | D11: 2067 | E11: 2818.6 | F11: 3268.4
A12: MRK_FULL_IS_CF_BS.xlsx | B12: Total Debt | C12: 33102 | D12: 30691 | E12: 35055 | F12: 37111
A13: MRK_FULL_IS_CF_BS.xlsx | B13: Cash And Cash Equivalents | C13: 8096 | D13: 12694 | E13: 6841 | F13: 13242
... A23: UNH_FULL_IS_CF_BS.xlsx | B23: Cash And Cash Equivalents | C23: 21375 | D23: 23365 | E23: 25427 | F23: 25312

Sheet Data (2)
A1: Source.Name | B1: Column1 | C1: Column2 | D1: Column3 | E1: Column4 | F1: Column5
A2: ABBV_FULL_IS_CF_BS.xlsx | B2: EBITDA | C2: 23933 | D2: 24174 | E2: 17172 | F2: 14910
A3: ABBV_FULL_IS_CF_BS.xlsx | B3: EBIT | C3: 15412 | D3: 15707 | E3: 8474 | F3: 6524
A4: AMGN_FULL_IS_CF_BS.xlsx | B4: EBITDA | C4: 11296 | D4: 12169 | E4: 14801 | F4: 13356
A5: AMGN_FULL_IS_CF_BS.xlsx | B5: EBIT | C5: 7898 | D5: 8752 | E5: 10730 | F5: 7764
A6: AZN_FULL_IS_CF_BS.xlsx | B6: EBITDA | C6: 5113 | D6: 9085 | E6: 13422 | F6: 15438
A7: AZN_FULL_IS_CF_BS.xlsx | B7: EBIT | C7: 1011 | D7: 3831 | E7: 8488 | F7: 10373
A8: BMY_FULL_IS_CF_BS.xlsx | B8: EBITDA | C8: 20118 | D8: 19221 | E8: 19366 | F8: 3168
A9: BMY_FULL_IS_CF_BS.xlsx | B9: EBIT | C9: 9432 | D9: 8945 | E9: 9606 | F9: -6432
A10: LLY_FULL_IS_CF_BS.xlsx | B10: EBITDA | C10: 8042.9 | D10: 8660.5 | E10: 8567.8 | F10: 15227.6
A11: LLY_FULL_IS_CF_BS.xlsx | B11: EBIT | C11: 6495.3 | D11: 7138 | E11: 7040.5 | F11: 13461
A12: MRK_FULL_IS_CF_BS.xlsx | B12: EBITDA | C12: 17899 | D12: 21315 | E12: 6907 | F12: 25706
A13: MRK_FULL_IS_CF_BS.xlsx | B13: EBIT | C13: 14685 | D13: 17406 | E13: 3035 | F13: 21207
... A21: UNH_FULL_IS_CF_BS.xlsx | B21: EBIT | C21: 23970 | D21: 28435 | E21: 32358 | F21: 23977

Sheet Data (3)
A1: Source.Name | B1: Column1 | C1: Column2 | D1: Column3 | E1: Column4 | F1: Column5
A2: ABBV_FULL_IS_CF_BS.xlsx | B2: Ordinary Shares Number | C2: 1768.3377 | D2: 1769.1813 | E2: 1765.9407 | F2: 1765.257
A3: AMGN_FULL_IS_CF_BS.xlsx | B3: Ordinary Shares Number | C3: 558.3 | D3: 534 | E3: 535.4 | F3: 537
A4: AZN_FULL_IS_CF_BS.xlsx | B4: Ordinary Shares Number | C4: 1549.4007 | D4: 1549.8 | E4: 1550.1626 | F4: 1550.1039
A5: BMY_FULL_IS_CF_BS.xlsx | B5: Ordinary Shares Number | C5: 2153 | D5: 2075 | E5: 2021 | F5: 2029
A6: LLY_FULL_IS_CF_BS.xlsx | B6: Ordinary Shares Number | C6: 953.653 | D6: 950.182 | E6: 899.379 | F6: 897.538
A7: MRK_FULL_IS_CF_BS.xlsx | B7: Ordinary Shares Number | C7: 2527.6045 | D7: 2537.8339 | E7: 2531.6333 | F7: 2527.6373
A8: NVO_FULL_IS_CF_BS.xlsx | B8: Ordinary Shares Number | C8: 4620 | D8: 4499.8 | E8: 4458.2879 | F8: 4441.3405
A9: PFE_FULL_IS_CF_BS.xlsx | B9: Ordinary Shares Number | C9: 5620 | D9: 5616 | E9: 5646 | F9: 5666.99
A10: RHHBY_FULL_IS_CF_BS.xlsx | B10: Ordinary Shares Number | C10: 800.40329 | D10: 799.18067 | E10: 797.24194 | F10: 795.4007
A11: SAN_FULL_IS_CF_BS.xlsx | B11: Ordinary Shares Number | C11: 17063.049 | D11: 16794.402 | E11: 15886.33 | F11: 15136.963
A12: UNH_FULL_IS_CF_BS.xlsx | B12: Ordinary Shares Number | C12: 941 | D12: 934 | E12: 924 | F12: 915

Sheet Sheet1
A1: Company | B1: Price(USD) | C1: Shares Outstanding(In Billions) | D1: Market Cap(In Billions) | E1: Total Debt(In Billions) | F1: Cash | G1: Enterprise Value | H1: EBITDA | I1: EV/EBITDA | J1: Weights
A2: Abbvie | B2: 228.5 | C2: =Data__3[[#This Row],[Column5]]/1000 -> 1.765257 | D2: =B2*C2 -> 403.36122 | E2: =Data[[#This Row],[Column5]]/1000 -> 67.144 | F2: ='Data (1)'!F3/1000 -> 5.524 | G2: =D2+E2-F2 -> 464.98122 | H2: =Data__2[[#This Row],[Column5]]/1000 -> 14.91 | I2: =G2/H2 -> 31.185863 | J2: =D2/$D$13 -> 0.19887085 | K2: =AVERAGE(I2:I4,I6:I11) -> 19.895365 | L2: =J2*I2 -> 6.2019591
A3: Amgen | B3: 327.3 | C3: =Data__3[[#This Row],[Column5]]/1000 -> 0.537 | D3: =B3*C3 -> 175.7601 | E3: ='Data (1)'!F4/1000 -> 60.099 | F3: ='Data (1)'!F5/1000 -> 11.973 | G3: =D3+E3-F3 -> 223.8861 | H3: ='Data (2)'!F4/1000 -> 13.356 | I3: =G3/H3 -> 16.76296 | J3: =D3/$D$13 -> 0.086655728 | L3: =J3*I3 -> 1.4526065
A4: Astrazeneca | B4: 92.51 | C4: =Data__3[[#This Row],[Column5]]/1000 -> 1.5501039 | D4: =B4*C4 -> 143.40011 | E4: ='Data (1)'!F6/1000 -> 30.114 | F4: ='Data (1)'!F7/1000 -> 5.488 | G4: =D4+E4-F4 -> 168.02611 | H4: ='Data (2)'!F6/1000 -> 15.438 | I4: =G4/H4 -> 10.88393 | J4: =D4/$D$13 -> 0.070701149 | L4: =J4*I4 -> 0.76950636
A5: Bristol Meyers | B5: 53.95 | C5: =Data__3[[#This Row],[Column5]]/1000 -> 2.029 | D5: =B5*C5 -> 109.46455 | E5: ='Data (1)'!F8/1000 -> 51.2 | F5: ='Data (1)'!F9/1000 -> 10.346 | G5: =D5+E5-F5 -> 150.31855 | H5: ='Data (2)'!F8/1000 -> 3.168 | I5: =G5/H5 -> 47.449037 | J5: =D5/$D$13 -> 0.053969759 | L5: =J5*I5 -> 2.5608131
A6: Eli Lilly | B6: 1075 | C6: =Data__3[[#This Row],[Column5]]/1000 -> 0.897538 | D6: =B6*C6 -> 964.85335 | E6: ='Data (1)'!F10/1000 -> 33.6442 | F6: ='Data (1)'!F11/1000 -> 3.2684 | G6: =D6+E6-F6 -> 995.22915 | H6: ='Data (2)'!F10/1000 -> 15.2276 | I6: =G6/H6 -> 65.356928 | J6: =D6/$D$13 -> 0.47570563 | L6: =J6*I6 -> 31.090659
A7: Merck | B7: 105.26 | C7: =Data__3[[#This Row],[Column5]]/1000 -> 2.5276373 | D7: =B7*C7 -> 266.05911 | E7: ='Data (1)'!F12/1000 -> 37.111 | F7: ='Data (1)'!F13/1000 -> 13.242 | G7: =D7+E7-F7 -> 289.92811 | H7: ='Data (2)'!F12/1000 -> 25.706 | I7: =G7/H7 -> 11.278616 | J7: =D7/$D$13 -> 0.13117622 | L7: =J7*I7 -> 1.4794862
A8: Novo Nordisk | B8: 50.88 | C8: =Data__3[[#This Row],[Column5]]/1000 -> 4.4413405 | D8: =B8*C8 -> 225.9754 | E8: ='Data (1)'!F14/1000 -> 102.787 | F8: ='Data (1)'!F15/1000 -> 15.655 | G8: =D8+E8-F8 -> 313.1074 | H8: ='Data (2)'!F14/1000 -> 137.376 | I8: =G8/H8 -> 2.2792002 | J8: =D8/$D$13 -> 0.11141359 | L8: =J8*I8 -> 0.25393386
A9: Pfizer | B9: 24.9 | C9: =Data__3[[#This Row],[Column5]]/1000 -> 5.66699 | D9: =B9*C9 -> 141.10805 | E9: ='Data (1)'!F16/1000 -> 63.649 | F9: ='Data (1)'!F17/1000 -> 1.043 | G9: =D9+E9-F9 -> 203.71405 | H9: ='Data (2)'!F16/1000 -> 18.127 | I9: =G9/H9 -> 11.238156 | J9: =D9/$D$13 -> 0.069571086 | L9: =J9*I9 -> 0.78185071
A10: Roche | B10: 328.2 | C10: =Data__3[[#This Row],[Column5]]/1000 -> 0.79540069 | D10: =B10*C10 -> 261.05051 | E10: ='Data (1)'!F18/1000 -> 36.354 | F10: ='Data (1)'!F19/1000 -> 6.975 | G10: =D10+E10-F10 -> 290.42951 | H10: ='Data (2)'!F18/1000 -> 16.619 | I10: =G10/H10 -> 17.475751 | J10: =D10/$D$13 -> 0.12870681 | L10: =J10*I10 -> 2.2492482
A11: United Health Group | B11: 330.14 | C11: ='Data (3)'!F12/1000 -> 0.915 | D11: =B11*C11 -> 302.0781 | E11: ='Data (1)'!F22/1000 -> 76.904 | F11: ='Data (1)'!F23/1000 -> 25.312 | G11: =D11+E11-F11 -> 353.6701 | H11: ='Data (2)'!F20/1000 -> 28.076 | I11: =G11/H11 -> 12.596883 | J11: =D11/$D$13 -> 0.14893481 | L11: =J11*I11 -> 1.8761145
A12: Johnson&Johnson | C12: 2.407 | E12: 36.634 | F12: 24.105 | H12: =24781/1000 -> 24.781 | L12: =SUM(L2:L5,L7:L11) -> 17.625519
B13: Equal Weighted | C13: M-Cap Weighted | D13: =SUM(D2:D5,D7:D11) -> 2028.2572
A14: Average Industry EV/EBITDA | B14: =AVERAGE(I2:I11) -> 22.650733 | C14: =L12 -> 17.625519
A16: Enterprise Value | B16: =K2*H12 -> 493.02705 | C16: =C14*H12 -> 436.77798
A17: Mcap | B17: =B16+E12-F12 -> 505.55605 | C17: =C16+E12-F12 -> 449.30698
A18: Share Price | B18: =B17/C12 -> 210.03575 | C18: =C17/C12 -> 186.6668
