Workbook

Sheet projectfinnman
P1: Method 1 : cost of equity using CAPM
A2: India Cements Limited | E2: Nifty 50(Proxy for Market Return) | I2: Nifty 50 Small Cap(Proxy for Small Cap Returns)
A3: Date | B3: Price | C3: change | D3: Change % | E3: Date | F3: Price | G3: change | H3: Change % | I3: Date | J3: Price | K3: Change | L3: Change % | M3: Excess Return from the market | O3: beta | P3: beta(regression) | S3: =(F4/F746)^(1/3) -> 1.1451568
A4: 45379 | B4: 212.4 | C4: =B4/B5-1 -> 0 | D4: 0 | E4: 45379 | F4: 22326.9 | G4: =F4/F5-1 -> 0.0091870012 | H4: 0.0092 | I4: 45379 | J4: 7029.95 | K4: =J4/J5-1 -> 0.00062628549 | L4: =K4/K5-1 -> -0.90051252 | M4: =K4-0.07 -> -0.069373715 | O4: =_xlfn.COVARIANCE.P(C4:C745,G4:G745)/_xlfn.VAR.P(G4:G745) -> 1.4987053 | P4: 1.4987053 | R4: Erm | S4: =S3-1 -> 0.14515679 | T4: Rf | U4: 0.065991 | AN4: Used for Beta analysis
A5: 45378 | B5: 212.4 | C5: =B5/B6-1 -> 0.015539087 | D5: 0.0155 | E5: 45378 | F5: 22123.65 | G5: =F5/F6-1 -> 0.0054056633 | H5: 0.0054 | I5: 45378 | J5: 7025.55 | K5: =J5/J6-1 -> 0.0062951186 | L5: =K5/K6-1 -> 3.34519 | M5: =K5-0.07 -> -0.063704881 | S5: 0.1452 | U5: =U4 -> 0.065991 | AO5: Coefficients | AP5: Standard Error | AQ5: t Stat | AR5: P-value | AS5: Lower 95% | AT5: Upper 95% | AU5: Lower 95.0% | AV5: Upper 95.0%
A6: 45377 | B6: 209.15 | C6: =B6/B7-1 -> 0.010142478 | D6: 0.0101 | E6: 45377 | F6: 22004.7 | G6: =F6/F7-1 -> -0.004165771 | H6: -0.0042 | I6: 45377 | J6: 6981.6 | K6: =J6/J7-1 -> 0.0014487556 | L6: =K6/K7-1 -> -0.79320133 | M6: =K6-0.07 -> -0.068551244 | AD6: India Cements Ltd: Significantly higher cost of equity (~18-20%) compared to the industry average (~10-12%). | AN6: Intercept | AO6: -0.00021338915 | AP6: 0.00087123836 | AQ6: -0.24492625 | AR6: 0.80658144 | AS6: -0.0019237825 | AT6: 0.0014970042 | AU6: -0.0019237825 | AV6: 0.0014970042
A7: 45373 | B7: 207.05 | C7: =B7/B8-1 -> 0.016445754 | D7: 0.0164 | E7: 45373 | F7: 22096.75 | G7: =F7/F8-1 -> 0.0038524529 | H7: 0.0039 | I7: 45373 | J7: 6971.5 | K7: =J7/J8-1 -> 0.0070056334 | L7: =K7/K8-1 -> -0.69994644 | M7: =K7-0.07 -> -0.062994367 | R7: premium | S7: =S4-U5 -> 0.079165794 | AN7: X Variable 1 | AO7: 1.4987053 | AP7: 0.10066425 | AQ7: 14.888157 | AR7: 4.8099353e-44 | AS7: 1.3010837 | AT7: 1.6963268 | AU7: 1.3010837 | AV7: 1.6963268
A8: 45372 | B8: 203.7 | C8: =B8/B9-1 -> 0.036113937 | D8: 0.0361 | E8: 45372 | F8: 22011.95 | G8: =F8/F9-1 -> 0.0079147034 | H8: 0.0079 | I8: 45372 | J8: 6923 | K8: =J8/J9-1 -> 0.023347943 | L8: =K8/K9-1 -> 262.22665 | M8: =K8-0.07 -> -0.046652057 | R8: beta premium | S8: =S7*O4 -> 0.11864619
A9: 45371 | B9: 196.6 | C9: =B9/B10-1 -> -0.011812013 | D9: -0.0118 | E9: 45371 | F9: 21839.1 | G9: =F9/F10-1 -> 0.00099232495 | H9: 0.001 | I9: 45371 | J9: 6765.05 | K9: =J9/J10-1 -> 8.8699007e-05 | L9: =K9/K10-1 -> -1.0085394 | M9: =K9-0.07 -> -0.069911301 | R9: Ke(ERi) | S9: =S8+U5 -> 0.18463719 | T9: =S9*100 -> 18.463719
A10: 45370 | B10: 198.95 | C10: =B10/B11-1 -> -0.02618698 | D10: -0.0262 | E10: 45370 | F10: 21817.45 | G10: =F10/F11-1 -> -0.010802196 | H10: -0.0108 | I10: 45370 | J10: 6764.45 | K10: =J10/J11-1 -> -0.010387026 | L10: =K10/K11-1 -> 1.0476898 | M10: =K10-0.07 -> -0.080387026 | R10: (cost of equity) | T10: 0.18463719
A11: 45369 | B11: 204.3 | C11: =B11/B12-1 -> -0.0034146341 | D11: -0.0034 | E11: 45369 | F11: 22055.7 | G11: =F11/F12-1 -> 0.0014688955 | H11: 0.0015 | I11: 45369 | J11: 6835.45 | K11: =J11/J12-1 -> -0.0050725587 | L11: =K11/K12-1 -> -2.2668253 | M11: =K11-0.07 -> -0.075072559
A12: 45366 | B12: 205 | C12: =B12/B13-1 -> 0.0039177277 | D12: 0.0039 | E12: 45366 | F12: 22023.35 | G12: =F12/F13-1 -> -0.0055674334 | H12: -0.0056 | I12: 45366 | J12: 6870.3 | K12: =J12/J13-1 -> 0.0040041503 | L12: =K12/K13-1 -> -0.88228047 | M12: =K12-0.07 -> -0.06599585
A13: 45365 | B13: 204.2 | C13: =B13/B14-1 -> 0.041571028 | D13: 0.0416 | E13: 45365 | F13: 22146.65 | G13: =F13/F14-1 -> 0.0067711624 | H13: 0.0068 | I13: 45365 | J13: 6842.9 | K13: =J13/J14-1 -> 0.034014325 | L13: =K13/K14-1 -> -1.6472823 | M13: =K13-0.07 -> -0.035985675 | R13: Cost of Equity Using CAPM Model
A14: 45364 | B14: 196.05 | C14: =B14/B15-1 -> -0.076760066 | D14: -0.0768 | E14: 45364 | F14: 21997.7 | G14: =F14/F15-1 -> -0.015132725 | H14: -0.0151 | I14: 45364 | J14: 6617.8 | K14: =J14/J15-1 -> -0.052549446 | L14: =K14/K15-1 -> 2.2167736 | M14: =K14-0.07 -> -0.12254945
A15: 45363 | B15: 212.35 | C15: =B15/B16-1 -> -0.034772727 | D15: -0.0348 | E15: 45363 | F15: 22335.7 | G15: =F15/F16-1 -> 0.00013657134 | H15: 0.0001 | I15: 45363 | J15: 6984.85 | K15: =J15/J16-1 -> -0.016336072 | L15: =K15/K16-1 -> -0.17614565 | M15: =K15-0.07 -> -0.086336072
A16: 45362 | B16: 220 | C16: =B16/B17-1 -> -0.024606517 | D16: -0.0246 | E16: 45362 | F16: 22332.65 | G16: =F16/F17-1 -> -0.0071531617 | H16: -0.0072 | I16: 45362 | J16: 7100.85 | K16: =J16/J17-1 -> -0.019828836 | L16: =K16/K17-1 -> -3.1452051 | M16: =K16-0.07 -> -0.089828836
A17: 45358 | B17: 225.55 | C17: =B17/B18-1 -> 0.0089465444 | D17: 0.0089 | E17: 45358 | F17: 22493.55 | G17: =F17/F18-1 -> 0.00086766738 | H17: 0.0009 | I17: 45358 | J17: 7244.5 | K17: =J17/J18-1 -> 0.0092433287 | L17: =K17/K18-1 -> -1.4424787 | M17: =K17-0.07 -> -0.060756671
A18: 45357 | B18: 223.55 | C18: =B18/B19-1 -> -0.020805957 | D18: -0.0208 | E18: 45357 | F18: 22474.05 | G18: =F18/F19-1 -> 0.0052669717 | H18: 0.0053 | I18: 45357 | J18: 7178.15 | K18: =J18/J19-1 -> -0.020889883 | L18: =K18/K19-1 -> 0.93886108 | M18: =K18-0.07 -> -0.090889883
A19: 45356 | B19: 228.3 | C19: =B19/B20-1 -> -0.016795866 | D19: -0.0168 | E19: 45356 | F19: 22356.3 | G19: =F19/F20-1 -> -0.0022003428 | H19: -0.0022 | I19: 45356 | J19: 7331.3 | K19: =J19/J20-1 -> -0.010774306 | L19: =K19/K20-1 -> 2.0296779 | M19: =K19-0.07 -> -0.080774306
A20: 45355 | B20: 232.2 | C20: =B20/B21-1 -> -0.0030055818 | D20: -0.003 | E20: 45355 | F20: 22405.6 | G20: =F20/F21-1 -> 0.0012154578 | H20: 0.0012 | I20: 45355 | J20: 7411.15 | K20: =J20/J21-1 -> -0.0035562547 | L20: =K20/K21-1 -> -1.4540562 | M20: =K20-0.07 -> -0.073556255 | AD20: India Cements Ltd: Beta is well above the industry average (>1.5 vs. ~1).
A21: 45353 | B21: 232.9 | C21: =B21/B22-1 -> 0.0075708414 | D21: 0.0076 | E21: 45353 | F21: 22378.4 | G21: =F21/F22-1 -> 0.0017749426 | H21: 0.0018 | I21: 45353 | J21: 7437.6 | K21: =J21/J22-1 -> 0.0078321906 | L21: =K21/K22-1 -> 1.0454538 | M21: =K21-0.07 -> -0.062167809
A22: 45352 | B22: 231.15 | C22: =B22/B23-1 -> 0.010050251 | D22: 0.0101 | E22: 45352 | F22: 22338.75 | G22: =F22/F23-1 -> 0.016192205 | H22: 0.0162 | I22: 45352 | J22: 7379.8 | K22: =J22/J23-1 -> 0.0038290724 | L22: =K22/K23-1 -> -0.21970651 | M22: =K22-0.07 -> -0.066170928
A23: 45351 | B23: 228.85 | C23: =B23/B24-1 -> 0.01914941 | D23: 0.0191 | E23: 45351 | F23: 21982.8 | G23: =F23/F24-1 -> 0.0014418379 | H23: 0.0014 | I23: 45351 | J23: 7351.65 | K23: =J23/J24-1 -> 0.0049072207 | L23: =K23/K24-1 -> -1.2389359 | M23: =K23-0.07 -> -0.065092779
A24: 45350 | B24: 224.55 | C24: =B24/B25-1 -> -0.041817794 | D24: -0.0418 | E24: 45350 | F24: 21951.15 | G24: =F24/F25-1 -> -0.011135963 | H24: -0.0111 | I24: 45350 | J24: 7315.75 | K24: =J24/J25-1 -> -0.020537812 | L24: =K24/K25-1 -> 13.02967 | M24: =K24-0.07 -> -0.090537812
A25: 45349 | B25: 234.35 | C25: =B25/B26-1 -> -0.019866165 | D25: -0.0199 | E25: 45349 | F25: 22198.35 | G25: =F25/F26-1 -> 0.0034490474 | H25: 0.0034 | I25: 45349 | J25: 7469.15 | K25: =J25/J26-1 -> -0.0014638842 | L25: =K25/K26-1 -> -0.68068416 | M25: =K25-0.07 -> -0.071463884
A26: 45348 | B26: 239.1 | C26: =B26/B27-1 -> -0.024678768 | D26: -0.0247 | E26: 45348 | F26: 22122.05 | G26: =F26/F27-1 -> -0.0040809987 | H26: -0.0041 | I26: 45348 | J26: 7480.1 | K26: =J26/J27-1 -> -0.0045844395 | L26: =K26/K27-1 -> -3.9025886 | M26: =K26-0.07 -> -0.07458444
A27: 45345 | B27: 245.15 | C27: =B27/B28-1 -> -0.012885041 | D27: -0.0129 | E27: 45345 | F27: 22212.7 | G27: =F27/F28-1 -> -0.00021379591 | H27: -0.0002 | I27: 45345 | J27: 7514.55 | K27: =J27/J28-1 -> 0.0015794314 | L27: =K27/K28-1 -> -0.81228231 | M27: =K27-0.07 -> -0.068420569
A28: 45344 | B28: 248.35 | C28: =B28/B29-1 -> 0.023069001 | D28: 0.0231 | E28: 45344 | F28: 22217.45 | G28: =F28/F29-1 -> 0.007363393 | H28: 0.0074 | I28: 45344 | J28: 7502.7 | K28: =J28/J29-1 -> 0.0084138654 | L28: =K28/K29-1 -> -1.9497672 | M28: =K28-0.07 -> -0.061586135
A29: 45343 | B29: 242.75 | C29: =B29/B30-1 -> -0.00041177682 | D29: -0.0004 | E29: 45343 | F29: 22055.05 | G29: =F29/F30-1 -> -0.0063927702 | H29: -0.0064 | I29: 45343 | J29: 7440.1 | K29: =J29/J30-1 -> -0.0088588709 | L29: =K29/K30-1 -> 0.69667613 | M29: =K29-0.07 -> -0.078858871
A30: 45342 | B30: 242.85 | C30: =B30/B31-1 -> 0.0064235392 | D30: 0.0064 | E30: 45342 | F30: 22196.95 | G30: =F30/F31-1 -> 0.0033766909 | H30: 0.0034 | I30: 45342 | J30: 7506.6 | K30: =J30/J31-1 -> -0.0052213093 | L30: =K30/K31-1 -> -5.9197787 | M30: =K30-0.07 -> -0.075221309
A31: 45341 | B31: 241.3 | C31: =B31/B32-1 -> -0.0084240805 | D31: -0.0084 | E31: 45341 | F31: 22122.25 | G31: =F31/F32-1 -> 0.0036999732 | H31: 0.0037 | I31: 45341 | J31: 7546 | K31: =J31/J32-1 -> 0.0010612895 | L31: =K31/K32-1 -> -0.56862886 | M31: =K31-0.07 -> -0.068938711
A32: 45338 | B32: 243.35 | C32: =B32/B33-1 -> 0.032894737 | D32: 0.0329 | E32: 45338 | F32: 22040.7 | G32: =F32/F33-1 -> 0.0059308787 | H32: 0.0059 | I32: 45338 | J32: 7538 | K32: =J32/J33-1 -> 0.00246027 | L32: =K32/K33-1 -> -0.82551144 | M32: =K32-0.07 -> -0.06753973
... A36: 45334 | B36: 235.15 | C36: =B36/B37-1 -> -0.048745955 | D36: -0.0487 | E36: 45334 | F36: 21616.05 | G36: =F36/F37-1 -> -0.0076414553 | H36: -0.0076 | I36: 45334 | J36: 7274.15 | K36: =J36/J37-1 -> -0.035501664 | L36: =K36/K37-1 -> 1.8376995 | M36: =K36-0.07 -> -0.10550166
A37: 45331 | B37: 247.2 | C37: =B37/B38-1 -> 0.041499895 | D37: 0.0415 | E37: 45331 | F37: 21782.5 | G37: =F37/F38-1 -> 0.0029721958 | H37: 0.003 | I37: 45331 | J37: 7541.9 | K37: =J37/J38-1 -> -0.01251072 | L37: =K37/K38-1 -> 1.114821 | M37: =K37-0.07 -> -0.08251072 | R37: COST OF DEBT
A38: 45330 | B38: 237.35 | C38: =B38/B39-1 -> -0.0098039216 | D38: -0.0098 | E38: 45330 | F38: 21717.95 | G38: =F38/F39-1 -> -0.0096919815 | H38: -0.0097 | I38: 45330 | J38: 7637.45 | K38: =J38/J39-1 -> -0.0059157349 | L38: =K38/K39-1 -> -1.7618208 | M38: =K38-0.07 -> -0.075915735 | R38: Year | S38: 2021 | T38: 2022 | U38: 2023 | V38: 2024
A39: 45329 | B39: 239.7 | C39: =B39/B40-1 -> -0.0056004978 | D39: -0.0056 | E39: 45329 | F39: 21930.5 | G39: =F39/F40-1 -> 5.0160971e-05 | H39: 0.0001 | I39: 45329 | J39: 7682.9 | K39: =J39/J40-1 -> 0.0077652583 | L39: =K39/K40-1 -> -0.16745298 | M39: =K39-0.07 -> -0.062234742 | R39: Total Debt (Crores) | S39: =463.64+1979.81 -> 2443.45 | T39: =1134.45+1928.7 -> 3063.15 | U39: =1119.32+1799.24 -> 2918.56 | V39: =1185.97+1415.26 -> 2601.23
A40: 45328 | B40: 241.05 | C40: =B40/B41-1 -> 0.030788967 | D40: 0.0308 | E40: 45328 | F40: 21929.4 | G40: =F40/F41-1 -> 0.007243348 | H40: 0.0072 | I40: 45328 | J40: 7623.7 | K40: =J40/J41-1 -> 0.0093271108 | L40: =K40/K41-1 -> 1.4713067 | M40: =K40-0.07 -> -0.060672889 | R40: Interest Paid(crores) | S40: 271 | T40: 198 | U40: 242 | V40: 244
A41: 45327 | B41: 233.85 | C41: =B41/B42-1 -> -0.026436303 | D41: -0.0264 | E41: 45327 | F41: 21771.7 | G41: =F41/F42-1 -> -0.0037567837 | H41: -0.0038 | I41: 45327 | J41: 7553.25 | K41: =J41/J42-1 -> 0.0037741616 | L41: =K41/K42-1 -> -0.60007835 | M41: =K41-0.07 -> -0.066225838 | R41: Average Interest rate(%) | S41: 0.0935 | T41: 0.0683 | U41: 0.0835 | V41: 0.0842 | AD41: India Cements Ltd: Lower WACC (~10-12%) than the industry average (~15-18%).
A42: 45324 | B42: 240.2 | C42: =B42/B43-1 -> -0.0082576383 | D42: -0.0083 | E42: 45324 | F42: 21853.8 | G42: =F42/F43-1 -> 0.0072059159 | H42: 0.0072 | I42: 45324 | J42: 7524.85 | K42: =J42/J43-1 -> 0.0094372527 | L42: =K42/K43-1 -> 2.6738088 | M42: =K42-0.07 -> -0.060562747 | R42: Taxable income(Crores) | S42: 322.71 | T42: 54.03 | U42: -406.91 | V42: -254.67
A43: 45323 | B43: 242.2 | C43: =B43/B44-1 -> -0.07345065 | D43: -0.0735 | E43: 45323 | F43: 21697.45 | G43: =F43/F44-1 -> -0.0013003033 | H43: -0.0013 | I43: 45323 | J43: 7454.5 | K43: =J43/J44-1 -> 0.0025687925 | L43: =K43/K44-1 -> -0.89158681 | M43: =K43-0.07 -> -0.067431207 | R43: Tax Paid (Crores) | S43: =322.71-222.04 -> 100.67 | T43: =T42-38.98 -> 15.05 | U43: 0 | V43: 0
A44: 45322 | B44: 261.4 | C44: =B44/B45-1 -> 0.004611837 | D44: 0.0046 | E44: 45322 | F44: 21725.7 | G44: =F44/F45-1 -> 0.0094600434 | H44: 0.0095 | I44: 45322 | J44: 7435.4 | K44: =J44/J45-1 -> 0.023694464 | L44: =K44/K45-1 -> 6.7460572 | M44: =K44-0.07 -> -0.046305536 | R44: Tax rate | S44: =S43/S42 -> 0.31195191 | T44: =T43/T42 -> 0.27854895 | U44: 0.25 | V44: 0.25
A45: 45321 | B45: 260.2 | C45: =B45/B46-1 -> 0.0071608283 | D45: 0.0072 | E45: 45321 | F45: 21522.1 | G45: =F45/F46-1 -> -0.0099136979 | H45: -0.0099 | I45: 45321 | J45: 7263.3 | K45: =J45/J46-1 -> 0.0030589064 | L45: =K45/K46-1 -> -0.7339216 | M45: =K45-0.07 -> -0.066941094 | R45: After Tax cost of debt | S45: =S41*(1-S44) -> 0.064332497 | T45: =T41*(1-T44) -> 0.049275106 | U45: =U41*(1-U44) -> 0.062625 | V45: =V41*(1-V44) -> 0.06315
A46: 45320 | B46: 258.35 | C46: =B46/B47-1 -> 0.022763262 | D46: 0.0228 | E46: 45320 | F46: 21737.6 | G46: =F46/F47-1 -> 0.018030591 | H46: 0.018 | I46: 45320 | J46: 7241.15 | K46: =J46/J47-1 -> 0.01149626 | L46: =K46/K47-1 -> 6.5737572 | M46: =K46-0.07 -> -0.05850374 | R46: Total Equity (crores) | S46: 310 | T46: 310 | U46: 310 | V46: 310
A47: 45316 | B47: 252.6 | C47: =B47/B48-1 -> 0.043801653 | D47: 0.0438 | E47: 45316 | F47: 21352.6 | G47: =F47/F48-1 -> -0.0047240718 | H47: -0.0047 | I47: 45316 | J47: 7158.85 | K47: =J47/J48-1 -> 0.0015179071 | L47: =K47/K48-1 -> -0.90625891 | M47: =K47-0.07 -> -0.068482093 | R47: weight of debt | S47: =S39/(S39+S40) -> 0.90016394 | T47: =T39/(T39+T40) -> 0.93928522 | U47: =U39/(U39+U40) -> 0.92343129 | V47: =V39/(V39+V40) -> 0.91424243
A48: 45315 | B48: 242 | C48: =B48/B49-1 -> 0.028255789 | D48: 0.0283 | E48: 45315 | F48: 21453.95 | G48: =F48/F49-1 -> 0.010130045 | H48: 0.0101 | I48: 45315 | J48: 7148 | K48: =J48/J49-1 -> 0.016192548 | L48: =K48/K49-1 -> -1.5373548 | M48: =K48-0.07 -> -0.053807452 | R48: weight of debt(%) | S48: =S47*100 -> 90.016394 | T48: =T47*100 -> 93.928522 | U48: =U47*100 -> 92.343129 | V48: =V47*100 -> 91.424243
A49: 45314 | B49: 235.35 | C49: =B49/B50-1 -> -0.064772501 | D49: -0.0648 | E49: 45314 | F49: 21238.8 | G49: =F49/F50-1 -> -0.01543682 | H49: -0.0154 | I49: 45314 | J49: 7034.1 | K49: =J49/J50-1 -> -0.030133813 | L49: =K49/K50-1 -> -28.288616 | M49: =K49-0.07 -> -0.10013381 | R49: weight of equity | S49: =1-S47 -> 0.099836063 | T49: =1-T47 -> 0.060714779 | U49: =1-U47 -> 0.076568709 | V49: =1-V47 -> 0.085757566
A50: 45311 | B50: 251.65 | C50: =B50/B51-1 -> -0.0057289609 | D50: -0.0057 | E50: 45311 | F50: 21571.8 | G50: =F50/F51-1 -> -0.0023401658 | H50: -0.0023 | I50: 45311 | J50: 7252.65 | K50: =J50/J51-1 -> 0.0011042631 | L50: =K50/K51-1 -> -0.86136627 | M50: =K50-0.07 -> -0.068895737 | R50: weight of equity(%) | S50: =S49*100 -> 9.9836063 | T50: =T49*100 -> 6.0714779 | U50: =U49*100 -> 7.6568709 | V50: =V49*100 -> 8.5757566
A51: 45310 | B51: 253.1 | C51: =B51/B52-1 -> 0.017487437 | D51: 0.0175 | E51: 45310 | F51: 21622.4 | G51: =F51/F52-1 -> 0.007461939 | H51: 0.0075 | I51: 45310 | J51: 7244.65 | K51: =J51/J52-1 -> 0.0079653282 | L51: =K51/K52-1 -> -4.0694627 | M51: =K51-0.07 -> -0.062034672 | R51: WACC(%) | S51: =(S47*S45)+(S49*S9) -> 0.076343244 | T51: =(T47*T45)+(T49*S9) -> 0.057493585 | U51: =(U47*U45)+(U49*S9) -> 0.071967316 | V51: =(V47*V45)+(V49*S9) -> 0.073568446
A52: 45309 | B52: 248.75 | C52: =B52/B53-1 -> -0.014265901 | D52: -0.0143 | E52: 45309 | F52: 21462.25 | G52: =F52/F53-1 -> -0.0050853075 | H52: -0.0051 | I52: 45309 | J52: 7187.4 | K52: =J52/J53-1 -> -0.0025950237 | L52: =K52/K53-1 -> -0.82855622 | M52: =K52-0.07 -> -0.072595024 | R52: WACC(%) | S52: =S51 -> 0.076343244 | T52: =T51 -> 0.057493585 | U52: =U51 -> 0.071967316 | V52: =V51 -> 0.073568446
A53: 45308 | B53: 252.35 | C53: =B53/B54-1 -> -0.022656855 | D53: -0.0227 | E53: 45308 | F53: 21571.95 | G53: =F53/F54-1 -> -0.020894323 | H53: -0.0209 | I53: 45308 | J53: 7206.1 | K53: =J53/J54-1 -> -0.015136295 | L53: =K53/K54-1 -> 0.96839908 | M53: =K53-0.07 -> -0.085136295 | R53: Average WACC | S53: =(S51+T51+U51+V51)/4 -> 0.069843148
A54: 45307 | B54: 258.2 | C54: =B54/B55-1 -> 0.0034978624 | D54: 0.0035 | E54: 45307 | F54: 22032.3 | G54: =F54/F55-1 -> -0.002948304 | H54: -0.0029 | I54: 45307 | J54: 7316.85 | K54: =J54/J55-1 -> -0.0076896475 | L54: =K54/K55-1 -> -15.530772 | M54: =K54-0.07 -> -0.077689647 | R54: Average WACC | S54: =AVERAGE(S52:V52) -> 0.069843148
A55: 45306 | B55: 257.3 | C55: =B55/B56-1 -> -0.00348567 | D55: -0.0035 | E55: 45306 | F55: 22097.45 | G55: =F55/F56-1 -> 0.0092671464 | H55: 0.0093 | I55: 45306 | J55: 7373.55 | K55: =J55/J56-1 -> 0.00052919745 | L55: =K55/K56-1 -> -0.93448347 | M55: =K55-0.07 -> -0.069470803
A56: 45303 | B56: 258.2 | C56: =B56/B57-1 -> 0.0019402406 | D56: 0.0019 | E56: 45303 | F56: 21894.55 | G56: =F56/F57-1 -> 0.01142642 | H56: 0.0114 | I56: 45303 | J56: 7369.65 | K56: =J56/J57-1 -> 0.0080773124 | L56: =K56/K57-1 -> 0.69120326 | M56: =K56-0.07 -> -0.061922688
A57: 45302 | B57: 257.7 | C57: =B57/B58-1 -> -0.0048271867 | D57: -0.0048 | E57: 45302 | F57: 21647.2 | G57: =F57/F58-1 -> 0.0013183031 | H57: 0.0013 | I57: 45302 | J57: 7310.6 | K57: =J57/J58-1 -> 0.0047760743 | L57: =K57/K58-1 -> -3.4179705 | M57: =K57-0.07 -> -0.065223926
A58: 45301 | B58: 258.95 | C58: =B58/B59-1 -> 0.0017408124 | D58: 0.0017 | E58: 45301 | F58: 21618.7 | G58: =F58/F59-1 -> 0.0034277333 | H58: 0.0034 | I58: 45301 | J58: 7275.85 | K58: =J58/J59-1 -> -0.0019752409 | L58: =K58/K59-1 -> -1.4678453 | M58: =K58-0.07 -> -0.071975241
A59: 45300 | B59: 258.5 | C59: =B59/B60-1 -> 0.0036886042 | D59: 0.0037 | E59: 45300 | F59: 21544.85 | G59: =F59/F60-1 -> 0.0014805002 | H59: 0.0015 | I59: 45300 | J59: 7290.25 | K59: =J59/J60-1 -> 0.0042219957 | L59: =K59/K60-1 -> -1.944406 | M59: =K59-0.07 -> -0.065778004
A60: 45299 | B60: 257.55 | C60: =B60/B61-1 -> -0.029760784 | D60: -0.0298 | E60: 45299 | F60: 21513 | G60: =F60/F61-1 -> -0.009110673 | H60: -0.0091 | I60: 45299 | J60: 7259.6 | K60: =J60/J61-1 -> -0.0044705302 | L60: =K60/K61-1 -> -1.529518 | M60: =K60-0.07 -> -0.07447053
A61: 45296 | B61: 265.45 | C61: =B61/B62-1 -> -0.028011717 | D61: -0.028 | E61: 45296 | F61: 21710.8 | G61: =F61/F62-1 -> 0.0024101281 | H61: 0.0024 | I61: 45296 | J61: 7292.2 | K61: =J61/J62-1 -> 0.0084426405 | L61: =K61/K62-1 -> -0.161702 | M61: =K61-0.07 -> -0.061557359
A62: 45295 | B62: 273.1 | C62: =B62/B63-1 -> 0.038600494 | D62: 0.0386 | E62: 45295 | F62: 21658.6 | G62: =F62/F63-1 -> 0.0065644701 | H62: 0.0066 | I62: 45295 | J62: 7231.15 | K62: =J62/J63-1 -> 0.010071169 | L62: =K62/K63-1 -> 15.564641 | M62: =K62-0.07 -> -0.059928831
A63: 45294 | B63: 262.95 | C63: =B63/B64-1 -> 0.0072782992 | D63: 0.0073 | E63: 45294 | F63: 21517.35 | G63: =F63/F64-1 -> -0.0068518125 | H63: -0.0069 | I63: 45294 | J63: 7159.05 | K63: =J63/J64-1 -> 0.00060799195 | L63: =K63/K64-1 -> -1.2236849 | M63: =K63-0.07 -> -0.069392008
A64: 45293 | B64: 261.05 | C64: =B64/B65-1 -> -0.00095675469 | D64: -0.001 | E64: 45293 | F64: 21665.8 | G64: =F64/F65-1 -> -0.0035001541 | H64: -0.0035 | I64: 45293 | J64: 7154.7 | K64: =J64/J65-1 -> -0.0027180731 | L64: =K64/K65-1 -> -1.4604648 | M64: =K64-0.07 -> -0.072718073
A65: 45292 | B65: 261.3 | C65: =B65/B66-1 -> 0.0092699884 | D65: 0.0093 | E65: 45292 | F65: 21741.9 | G65: =F65/F66-1 -> 0.00048317182 | H65: 0.0005 | I65: 45292 | J65: 7174.2 | K65: =J65/J66-1 -> 0.0059028898 | L65: =K65/K66-1 -> -0.24114358 | M65: =K65-0.07 -> -0.06409711
A66: 45289 | B66: 258.9 | C66: =B66/B67-1 -> 0.0052417006 | D66: 0.0052 | E66: 45289 | F66: 21731.4 | G66: =F66/F67-1 -> -0.0021718468 | H66: -0.0022 | I66: 45289 | J66: 7132.1 | K66: =J66/J67-1 -> 0.0077786648 | L66: =K66/K67-1 -> -0.27377866 | M66: =K66-0.07 -> -0.062221335
... A119: 45211 | B119: 228.7 | C119: =B119/B120-1 -> -0.00065545117 | D119: -0.0007 | E119: 45211 | F119: 19794 | G119: =F119/F120-1 -> -0.00087576061 | H119: -0.0009 | I119: 45211 | J119: 5983.6 | K119: =J119/J120-1 -> 0.0083246267 | L119: =K119/K120-1 -> -0.10604152 | M119: =K119-0.07 -> -0.061675373
A120: 45210 | B120: 228.85 | C120: =B120/B121-1 -> 0.0013126231 | D120: 0.0013 | E120: 45210 | F120: 19811.35 | G120: =F120/F121-1 -> 0.006170692 | H120: 0.0062 | I120: 45210 | J120: 5934.2 | K120: =J120/J121-1 -> 0.0093120955 | L120: =K120/K121-1 -> -0.22828499 | M120: =K120-0.07 -> -0.060687904 | R120: Variance of the stock | U120: Variance of the market
A121: 45209 | B121: 228.55 | C121: =B121/B122-1 -> 0.015777778 | D121: 0.0158 | E121: 45209 | F121: 19689.85 | G121: =F121/F122-1 -> 0.0090968028 | H121: 0.0091 | I121: 45209 | J121: 5879.45 | K121: =J121/J122-1 -> 0.012066754 | L121: =K121/K122-1 -> -1.6376803 | M121: =K121-0.07 -> -0.057933246 | R121: =_xlfn.VAR.P(C11:C752) -> 0.00072986352 | U121: =_xlfn.VAR.P(G10:G752) -> 7.4920996e-05 | AG121: India Cements Ltd: Highest unsystematic risk among all companies in the chart, with a value significantly above the industry average.
A122: 45208 | B122: 225 | C122: =B122/B123-1 -> -0.026816609 | D122: -0.0268 | E122: 45208 | F122: 19512.35 | G122: =F122/F123-1 -> -0.0071819269 | H122: -0.0072 | I122: 45208 | J122: 5809.35 | K122: =J122/J123-1 -> -0.01892289 | L122: =K122/K123-1 -> -4.8515434 | M122: =K122-0.07 -> -0.08892289 | R122: =R121-W123 -> 0.00072986335 | S122: UNSYSTEMATIC RISK | W122: systematic Risk
A123: 45205 | B123: 231.2 | C123: =B123/B124-1 -> 0.0080662743 | D123: 0.0081 | E123: 45205 | F123: 19653.5 | G123: =F123/F124-1 -> 0.0055127074 | H123: 0.0055 | I123: 45205 | J123: 5921.4 | K123: =J123/J124-1 -> 0.0049130667 | L123: =K123/K124-1 -> -0.22248063 | M123: =K123-0.07 -> -0.065086933 | W123: =U121*H11^2 -> 1.6857224e-10
A124: 45204 | B124: 229.35 | C124: =B124/B125-1 -> -0.0060671723 | D124: -0.0061 | E124: 45204 | F124: 19545.75 | G124: =F124/F125-1 -> 0.0056415639 | H124: 0.0056 | I124: 45204 | J124: 5892.45 | K124: =J124/J125-1 -> 0.0063188995 | L124: =K124/K125-1 -> -1.5528477 | M124: =K124-0.07 -> -0.063681101
A125: 45203 | B125: 230.75 | C125: =B125/B126-1 -> -0.0085929108 | D125: -0.0086 | E125: 45203 | F125: 19436.1 | G125: =F125/F126-1 -> -0.0047442873 | H125: -0.0047 | I125: 45203 | J125: 5855.45 | K125: =J125/J126-1 -> -0.011429729 | L125: =K125/K126-1 -> -2.687441 | M125: =K125-0.07 -> -0.081429729
A126: 45202 | B126: 232.75 | C126: =B126/B127-1 -> -0.0019296741 | D126: -0.0019 | E126: 45202 | F126: 19528.75 | G126: =F126/F127-1 -> -0.0055783851 | H126: -0.0056 | I126: 45202 | J126: 5923.15 | K126: =J126/J127-1 -> 0.0067734095 | L126: =K126/K127-1 -> -0.45787534 | M126: =K126-0.07 -> -0.063226591
A127: 45198 | B127: 233.2 | C127: =B127/B128-1 -> 0.028899184 | D127: 0.0289 | E127: 45198 | F127: 19638.3 | G127: =F127/F128-1 -> 0.0058775172 | H127: 0.0059 | I127: 45198 | J127: 5883.3 | K127: =J127/J128-1 -> 0.012494192 | L127: =K127/K128-1 -> -2.4587093 | M127: =K127-0.07 -> -0.057505808
A128: 45197 | B128: 226.65 | C128: =B128/B129-1 -> -0.025370888 | D128: -0.0254 | E128: 45197 | F128: 19523.55 | G128: =F128/F129-1 -> -0.0097837085 | H128: -0.0098 | I128: 45197 | J128: 5810.7 | K128: =J128/J129-1 -> -0.0085652374 | L128: =K128/K129-1 -> -1.8070318 | M128: =K128-0.07 -> -0.078565237
A129: 45196 | B129: 232.55 | C129: =B129/B130-1 -> 0.00086077039 | D129: 0.0009 | E129: 45196 | F129: 19716.45 | G129: =F129/F130-1 -> 0.0026316191 | H129: 0.0026 | I129: 45196 | J129: 5860.9 | K129: =J129/J130-1 -> 0.010613258 | L129: =K129/K130-1 -> 0.47610172 | M129: =K129-0.07 -> -0.059386742
A130: 45195 | B130: 232.35 | C130: =B130/B131-1 -> -0.0019329897 | D130: -0.0019 | E130: 45195 | F130: 19664.7 | G130: =F130/F131-1 -> -0.00050064677 | H130: -0.0005 | I130: 45195 | J130: 5799.35 | K130: =J130/J131-1 -> 0.007190059 | L130: =K130/K131-1 -> 0.73596784 | M130: =K130-0.07 -> -0.062809941
A131: 45194 | B131: 232.8 | C131: =B131/B132-1 -> -0.0029978587 | D131: -0.003 | E131: 45194 | F131: 19674.55 | G131: =F131/F132-1 -> 1.5248358e-05 | H131: 0 | I131: 45194 | J131: 5757.95 | K131: =J131/J132-1 -> 0.0041418158 | L131: =K131/K132-1 -> 3.3536563 | M131: =K131-0.07 -> -0.065858184
A132: 45191 | B132: 233.5 | C132: =B132/B133-1 -> 0.016543317 | D132: 0.0165 | E132: 45191 | F132: 19674.25 | G132: =F132/F133-1 -> -0.0034494374 | H132: -0.0034 | I132: 45191 | J132: 5734.2 | K132: =J132/J133-1 -> 0.00095134192 | L132: =K132/K133-1 -> -1.0690338 | M132: =K132-0.07 -> -0.069048658
A133: 45190 | B133: 229.7 | C133: =B133/B134-1 -> -0.038509837 | D133: -0.0385 | E133: 45190 | F133: 19742.35 | G133: =F133/F134-1 -> -0.0079919001 | H133: -0.008 | I133: 45190 | J133: 5728.75 | K133: =J133/J134-1 -> -0.013780815 | L133: =K133/K134-1 -> 0.93805966 | M133: =K133-0.07 -> -0.083780815
A134: 45189 | B134: 238.9 | C134: =B134/B135-1 -> -0.021903787 | D134: -0.0219 | E134: 45189 | F134: 19901.4 | G134: =F134/F135-1 -> -0.011518231 | H134: -0.0115 | I134: 45189 | J134: 5808.8 | K134: =J134/J135-1 -> -0.0071106249 | L134: =K134/K135-1 -> 1.6909816 | M134: =K134-0.07 -> -0.077110625
A135: 45187 | B135: 244.25 | C135: =B135/B136-1 -> -0.012732417 | D135: -0.0127 | E135: 45187 | F135: 20133.3 | G135: =F135/F136-1 -> -0.0029243748 | H135: -0.0029 | I135: 45187 | J135: 5850.4 | K135: =J135/J136-1 -> -0.0026423908 | L135: =K135/K136-1 -> -1.5201232 | M135: =K135-0.07 -> -0.072642391
... A139: 45181 | B139: 234.45 | C139: =B139/B140-1 -> -0.065936255 | D139: -0.0659 | E139: 45181 | F139: 19993.2 | G139: =F139/F140-1 -> -0.00015752875 | H139: -0.0002 | I139: 45181 | J139: 5739.25 | K139: =J139/J140-1 -> -0.042724422 | L139: =K139/K140-1 -> -4.1002204 | M139: =K139-0.07 -> -0.11272442
A140: 45180 | B140: 251 | C140: =B140/B141-1 -> 0.0094510356 | D140: 0.0095 | E140: 45180 | F140: 19996.35 | G140: =F140/F141-1 -> 0.0089001234 | H140: 0.0089 | I140: 45180 | J140: 5995.4 | K140: =J140/J141-1 -> 0.013781092 | L140: =K140/K141-1 -> 0.52105883 | M140: =K140-0.07 -> -0.056218908 | R140: Dividend Yield
A141: 45177 | B141: 248.65 | C141: =B141/B142-1 -> -0.0097570689 | D141: -0.0098 | E141: 45177 | F141: 19819.95 | G141: =F141/F142-1 -> 0.0047092698 | H141: 0.0047 | I141: 45177 | J141: 5913.9 | K141: =J141/J142-1 -> 0.0090601966 | L141: =K141/K142-1 -> 0.49306144 | M141: =K141-0.07 -> -0.060939803 | R141: Year | S141: price of the stock (Rs) | T141: Dividend (Rs) | U141: Dividend Yield
A142: 45176 | B142: 251.1 | C142: =B142/B143-1 -> -0.011027964 | D142: -0.011 | E142: 45176 | F142: 19727.05 | G142: =F142/F143-1 -> 0.0059150326 | H142: 0.0059 | I142: 45176 | J142: 5860.8 | K142: =J142/J143-1 -> 0.0060682007 | L142: =K142/K143-1 -> -7.4923067 | M142: =K142-0.07 -> -0.063931799 | R142: 2021 | S142: 163.6 | T142: 1 | U142: =projectfinnman!$T142/projectfinnman!$S142 -> 0.0061124694
A143: 45175 | B143: 253.9 | C143: =B143/B144-1 -> -0.003727683 | D143: -0.0037 | E143: 45175 | F143: 19611.05 | G143: =F143/F144-1 -> 0.0018467527 | H143: 0.0018 | I143: 45175 | J143: 5825.45 | K143: =J143/J144-1 -> -0.00093467561 | L143: =K143/K144-1 -> -1.1459656 | M143: =K143-0.07 -> -0.070934676 | R143: 2022 | S143: 242 | T143: 1 | U143: =projectfinnman!$T143/projectfinnman!$S143 -> 0.0041322314 | AG143: India Cements Ltd: The lowest dividend yield among the companies as well as comparing to the Industry Average.
A144: 45174 | B144: 254.85 | C144: =B144/B145-1 -> -0.011059371 | D144: -0.0111 | E144: 45174 | F144: 19574.9 | G144: =F144/F145-1 -> 0.0023606161 | H144: 0.0024 | I144: 45174 | J144: 5830.9 | K144: =J144/J145-1 -> 0.0064033967 | L144: =K144/K145-1 -> -0.5652619 | M144: =K144-0.07 -> -0.063596603 | R144: 2023 | S144: 187.15 | T144: 0 | U144: =projectfinnman!$T144/projectfinnman!$S144 -> 0
A145: 45173 | B145: 257.7 | C145: =B145/B146-1 -> -0.012454493 | D145: -0.0125 | E145: 45173 | F145: 19528.8 | G145: =F145/F146-1 -> 0.0048108339 | H145: 0.0048 | I145: 45173 | J145: 5793.8 | K145: =J145/J146-1 -> 0.01472932 | L145: =K145/K146-1 -> -0.083389342 | M145: =K145-0.07 -> -0.05527068 | R145: 2024 | S145: 212.4 | T145: 0 | U145: =projectfinnman!$T145/projectfinnman!$S145 -> 0
A146: 45170 | B146: 260.95 | C146: =B146/B147-1 -> 0.10408293 | D146: 0.1041 | E146: 45170 | F146: 19435.3 | G146: =F146/F147-1 -> 0.0094267106 | H146: 0.0094 | I146: 45170 | J146: 5709.7 | K146: =J146/J147-1 -> 0.016069331 | L146: =K146/K147-1 -> 3.4212771 | M146: =K146-0.07 -> -0.053930669 | T146: AVERAGE | U146: =AVERAGE(U142:U145) -> 0.0025611752
A147: 45169 | B147: 236.35 | C147: =B147/B148-1 -> -0.0081829627 | D147: -0.0082 | E147: 45169 | F147: 19253.8 | G147: =F147/F148-1 -> -0.0048404312 | H147: -0.0048 | I147: 45169 | J147: 5619.4 | K147: =J147/J148-1 -> 0.0036345451 | L147: =K147/K148-1 -> -0.73121152 | M147: =K147-0.07 -> -0.066365455
A148: 45168 | B148: 238.3 | C148: =B148/B149-1 -> -0.020752003 | D148: -0.0208 | E148: 45168 | F148: 19347.45 | G148: =F148/F149-1 -> 0.00024815628 | H148: 0.0002 | I148: 45168 | J148: 5599.05 | K148: =J148/J149-1 -> 0.013521953 | L148: =K148/K149-1 -> 1.1330298 | M148: =K148-0.07 -> -0.056478047
A149: 45167 | B149: 243.35 | C149: =B149/B150-1 -> 0.015015641 | D149: 0.015 | E149: 45167 | F149: 19342.65 | G149: =F149/F150-1 -> 0.0018957788 | H149: 0.0019 | I149: 45167 | J149: 5524.35 | K149: =J149/J150-1 -> 0.0063393174 | L149: =K149/K150-1 -> -0.37072288 | M149: =K149-0.07 -> -0.063660683
A150: 45166 | B150: 239.75 | C150: =B150/B151-1 -> 0.039904576 | D150: 0.0399 | E150: 45166 | F150: 19306.05 | G150: =F150/F151-1 -> 0.0020891943 | H150: 0.0021 | I150: 45166 | J150: 5489.55 | K150: =J150/J151-1 -> 0.010073968 | L150: =K150/K151-1 -> -19.889384 | M150: =K150-0.07 -> -0.059926032
A151: 45163 | B151: 230.55 | C151: =B151/B152-1 -> -0.023713741 | D151: -0.0237 | E151: 45163 | F151: 19265.8 | G151: =F151/F152-1 -> -0.0062362341 | H151: -0.0062 | I151: 45163 | J151: 5434.8 | K151: =J151/J152-1 -> -0.00053331372 | L151: =K151/K152-1 -> -0.83469396 | M151: =K151-0.07 -> -0.070533314 | S151: Method 2 : cost of equity using DDM
A152: 45162 | B152: 236.15 | C152: =B152/B153-1 -> -0.011304166 | D152: -0.0113 | E152: 45162 | F152: 19386.7 | G152: =F152/F153-1 -> -0.0029469245 | H152: -0.0029 | I152: 45162 | J152: 5437.7 | K152: =J152/J153-1 -> -0.0032262204 | L152: =K152/K153-1 -> -1.2246055 | M152: =K152-0.07 -> -0.07322622
A153: 45161 | B153: 238.85 | C153: =B153/B154-1 -> -0.0045842884 | D153: -0.0046 | E153: 45161 | F153: 19444 | G153: =F153/F154-1 -> 0.0024514795 | H153: 0.0025 | I153: 45161 | J153: 5455.3 | K153: =J153/J154-1 -> 0.014363942 | L153: =K153/K154-1 -> 0.66134105 | M153: =K153-0.07 -> -0.055636058
A154: 45160 | B154: 239.95 | C154: =B154/B155-1 -> -0.020612245 | D154: -0.0206 | E154: 45160 | F154: 19396.45 | G154: =F154/F155-1 -> 0.0001469557 | H154: 0.0001 | I154: 45160 | J154: 5378.05 | K154: =J154/J155-1 -> 0.0086459926 | L154: =K154/K155-1 -> 1.3494103 | M154: =K154-0.07 -> -0.061354007 | S154: Cost of Equity(Ke) Using DDM Model
A155: 45159 | B155: 245 | C155: =B155/B156-1 -> 0.033973412 | D155: 0.034 | E155: 45159 | F155: 19393.6 | G155: =F155/F156-1 -> 0.0043215615 | H155: 0.0043 | I155: 45159 | J155: 5331.95 | K155: =J155/J156-1 -> 0.0036800693 | L155: =K155/K156-1 -> -1.6789823 | M155: =K155-0.07 -> -0.066319931 | R155: Year | S155: Retention Ratio | T155: ROE | U155: g=Retention Ratio*ROE | V155: Ke | W155: COST OF EQUITY
A156: 45156 | B156: 236.95 | C156: =B156/B157-1 -> -0.017008919 | D156: -0.017 | E156: 45156 | F156: 19310.15 | G156: =F156/F157-1 -> -0.0028453028 | H156: -0.0028 | I156: 45156 | J156: 5312.4 | K156: =J156/J157-1 -> -0.0054199781 | L156: =K156/K157-1 -> -3.4584098 | M156: =K156-0.07 -> -0.075419978 | R156: 2022 | S156: 0.2051 | T156: 0.0072 | U156: =S156*T156 -> 0.00147672 | V156: =T142/S142+U156 -> 0.0075891894 | W156: =projectfinnman!$V156 -> 0.0075891894
A157: 45155 | B157: 241.05 | C157: =B157/B158-1 -> -0.023298217 | D157: -0.0233 | E157: 45155 | F157: 19365.25 | G157: =F157/F158-1 -> -0.0051245826 | H157: -0.0051 | I157: 45155 | J157: 5341.35 | K157: =J157/J158-1 -> 0.0022046683 | L157: =K157/K158-1 -> -3.158168 | M157: =K157-0.07 -> -0.067795332 | R157: 2021 | S157: 0.9163 | T157: 0.0395 | U157: =S157*T157 -> 0.03619385 | V157: =T143/S143+U157 -> 0.040326081 | W157: =projectfinnman!$V157 -> 0.040326081
A158: 45154 | B158: 246.8 | C158: =B158/B159-1 -> -0.020246129 | D158: -0.0202 | E158: 45154 | F158: 19465 | G158: =F158/F159-1 -> 0.0015667973 | H158: 0.0016 | I158: 45154 | J158: 5329.6 | K158: =J158/J159-1 -> -0.0010215462 | L158: =K158/K159-1 -> -0.78483307 | M158: =K158-0.07 -> -0.071021546
...

Sheet Fama French Model
B1: Mkt-RF | C1: SMB | D1: HML | E1: RF | F1: Change | G1: Excess Return from the market | J1: Mkt-RF | K1: SMB | L1: HML | M1: RF
A2: 20210401 | B2: 1.27 | C2: 0.29 | D2: -0.02 | E2: 0 | F2: 0.00062628549 | G2: -0.069373715 | J2: 1.27 | K2: 0.29 | L2: -0.02
A3: 20210405 | B3: 1.27 | C3: -0.57 | D3: -0.72 | E3: 0 | F3: 0.0062951186 | G3: -0.063704881 | J3: =AVERAGE(B2:B743) -> 0.029245283 | K3: =AVERAGE(C2:C743) -> -0.033679245 | L3: =AVERAGE(D2:D743) -> 0.022493261 | M3: =AVERAGE(E2:E743) -> 0.0098045822
A4: 20210406 | B4: 0.01 | C4: -0.32 | D4: 0.1 | E4: 0 | F4: 0.0014487556 | G4: -0.068551244
A5: 20210407 | B5: -0.12 | C5: -1.6 | D5: 0.3 | E5: 0 | F5: 0.0070056334 | G5: -0.062994367
A6: 20210408 | B6: 0.62 | C6: 0.6 | D6: -1.16 | E6: 0 | F6: 0.023347943 | G6: -0.046652057
A7: 20210409 | B7: 0.65 | C7: -0.64 | D7: 0.13 | E7: 0 | F7: 8.8699007e-05 | G7: -0.069911301 | J7: Cost of equity | P7: Coefficients | Q7: Standard Error | R7: t Stat | S7: P-value | T7: Lower 95% | U7: Upper 95% | V7: Lower 95.0% | W7: Upper 95.0%
A8: 20210412 | B8: -0.05 | C8: -0.6 | D8: 0.58 | E8: 0 | F8: -0.010387026 | G8: -0.080387026 | J8: =M3+(J2*J3+K2*K3+L2*L3)*756 -> 20.36485 | K8: % | O8: Intercept | P8: -0.069262188 | Q8: 0.0004605728 | R8: -150.38271 | S8: 0 | T8: -0.070166379 | U8: -0.068357997 | V8: -0.070166379 | W8: -0.068357997
A9: 20210413 | B9: 0.41 | C9: -0.3 | D9: -1.58 | E9: 0 | F9: -0.0050725587 | G9: -0.075072559 | O9: 1.27 | P9: 0.00061853941 | Q9: 0.00044850695 | R9: 1.3791077 | S9: 0.1682799 | T9: -0.00026196406 | U9: 0.0014990429 | V9: -0.00026196406 | W9: 0.0014990429
A10: 20210414 | B10: -0.35 | C10: 0.78 | D10: 1.42 | E10: 0 | F10: 0.0040041503 | G10: -0.06599585 | O10: 0.29 | P10: -0.00066866717 | Q10: 0.0006959759 | R10: -0.96076196 | S10: 0.33698696 | T10: -0.0020349987 | U10: 0.00069766438 | V10: -0.0020349987 | W10: 0.00069766438
A11: 20210415 | B11: 1.04 | C11: -0.43 | D11: -1.18 | E11: 0 | F11: 0.034014325 | G11: -0.035985675 | O11: -0.02 | P11: 0.0008055024 | Q11: 0.00049467238 | R11: 1.6283553 | S11: 0.10387693 | T11: -0.00016563248 | U11: 0.0017766373 | V11: -0.00016563248 | W11: 0.0017766373
A12: 20210416 | B12: 0.27 | C12: -0.35 | D12: 0.64 | E12: 0 | F12: -0.052549446 | G12: -0.12254945
A13: 20210419 | B13: -0.73 | C13: -0.77 | D13: 0.78 | E13: 0 | F13: -0.016336072 | G13: -0.086336072 | I13: Method 5: calculate the cost of equity using the Fama French Model
A14: 20210420 | B14: -0.94 | C14: -1.18 | D14: -1.57 | E14: 0 | F14: -0.019828836 | G14: -0.089828836
A15: 20210421 | B15: 1.11 | C15: 1.38 | D15: 0.11 | E15: 0 | F15: 0.0092433287 | G15: -0.060756671
A16: 20210422 | B16: -0.77 | C16: 0.65 | D16: -0.78 | E16: 0 | F16: -0.020889883 | G16: -0.090889883
A17: 20210423 | B17: 1.26 | C17: 0.74 | D17: 0.7 | E17: 0 | F17: -0.010774306 | G17: -0.080774306
A18: 20210426 | B18: 0.43 | C18: 0.86 | D18: -0.48 | E18: 0 | F18: -0.0035562547 | G18: -0.073556255
A19: 20210427 | B19: -0.03 | C19: -0.16 | D19: 0.86 | E19: 0 | F19: 0.0078321906 | G19: -0.062167809
A20: 20210428 | B20: -0.06 | C20: 0.19 | D20: 0.2 | E20: 0 | F20: 0.0038290724 | G20: -0.066170928
A21: 20210429 | B21: 0.39 | C21: -1.13 | D21: 1.07 | E21: 0 | F21: 0.0049072207 | G21: -0.065092779
A22: 20210430 | B22: -0.83 | C22: -0.42 | D22: -0.32 | E22: 0 | F22: -0.020537812 | G22: -0.090537812
A23: 20210503 | B23: 0.17 | C23: 0.46 | D23: 1.7 | E23: 0 | F23: -0.0014638842 | G23: -0.071463884
A24: 20210504 | B24: -0.89 | C24: -0.75 | D24: 1.99 | E24: 0 | F24: -0.0045844395 | G24: -0.07458444
A25: 20210505 | B25: -0.05 | C25: -0.46 | D25: 1.33 | E25: 0 | F25: 0.0015794314 | G25: -0.068420569
... A743: 20240313 | B743: -0.14 | C743: 0.3 | D743: -0.04 | E743: 0.021 | F743: -0.013496012 | G743: -0.083496012
G744: -0.065991

Sheet ultrattech
A1: Date | B1: Price | C1: change | D1: Change % | E1: Date | F1: Price | G1: change | H1: Change % | I1: beta | J1: beta(regression) | M1: =(F2/F744)^(1/3) -> 1.1451568
A2: 45379 | B2: 9749.15 | C2: =B2/B3-1 -> 0.013061844 | D2: 0.0131 | E2: 45379 | F2: 22326.9 | G2: =F2/F3-1 -> 0.0091870012 | H2: 0.0092 | I2: =_xlfn.COVARIANCE.P(C2:C743,G2:G743)/_xlfn.VAR.P(G2:G743) -> 0.91908624 | J2: 1.4987053 | L2: Erm | M2: =M1-1 -> 0.14515679 | N2: Rf | O2: 0.065991
A3: 45378 | B3: 9623.45 | C3: =B3/B4-1 -> 0.0023696189 | D3: 0.0024 | E3: 45378 | F3: 22123.65 | G3: =F3/F4-1 -> 0.0054056633 | H3: 0.0054 | M3: 0.1452 | O3: =O2 -> 0.065991
A4: 45377 | B4: 9600.7 | C4: =B4/B5-1 -> -0.0083714205 | D4: -0.0084 | E4: 45377 | F4: 22004.7 | G4: =F4/F5-1 -> -0.004165771 | H4: -0.0042
A5: 45373 | B5: 9681.75 | C5: =B5/B6-1 -> 0.0084368409 | D5: 0.0084 | E5: 45373 | F5: 22096.75 | G5: =F5/F6-1 -> 0.0038524529 | H5: 0.0039 | L5: premium | M5: =M2-O3 -> 0.079165794
A6: 45372 | B6: 9600.75 | C6: =B6/B7-1 -> 0.012251504 | D6: 0.0123 | E6: 45372 | F6: 22011.95 | G6: =F6/F7-1 -> 0.0079147034 | H6: 0.0079 | L6: beta premium | M6: =M5*I2 -> 0.072760192
A7: 45371 | B7: 9484.55 | C7: =B7/B8-1 -> 0.0033110306 | D7: 0.0033 | E7: 45371 | F7: 21839.1 | G7: =F7/F8-1 -> 0.00099232495 | H7: 0.001 | L7: Ke(ERi) | M7: =M6+O3 -> 0.13875119 | N7: =M7*100 -> 13.875119
A8: 45370 | B8: 9453.25 | C8: =B8/B9-1 -> -0.016449302 | D8: -0.0164 | E8: 45370 | F8: 21817.45 | G8: =F8/F9-1 -> -0.010802196 | H8: -0.0108 | L8: (cost of equity) | N8: =M7 -> 0.13875119
A9: 45369 | B9: 9611.35 | C9: =B9/B10-1 -> -0.0022423038 | D9: -0.0022 | E9: 45369 | F9: 22055.7 | G9: =F9/F10-1 -> 0.0014688955 | H9: 0.0015
A10: 45366 | B10: 9632.95 | C10: =B10/B11-1 -> -0.0066000134 | D10: -0.0066 | E10: 45366 | F10: 22023.35 | G10: =F10/F11-1 -> -0.0055674334 | H10: -0.0056
A11: 45365 | B11: 9696.95 | C11: =B11/B12-1 -> 0.010778075 | D11: 0.0108 | E11: 45365 | F11: 22146.65 | G11: =F11/F12-1 -> 0.0067711624 | H11: 0.0068
A12: 45364 | B12: 9593.55 | C12: =B12/B13-1 -> -0.0022827726 | D12: -0.0023 | E12: 45364 | F12: 21997.7 | G12: =F12/F13-1 -> -0.015132725 | H12: -0.0151
A13: 45363 | B13: 9615.5 | C13: =B13/B14-1 -> -0.0084966848 | D13: -0.0085 | E13: 45363 | F13: 22335.7 | G13: =F13/F14-1 -> 0.00013657134 | H13: 0.0001
A14: 45362 | B14: 9697.9 | C14: =B14/B15-1 -> 0.0025586288 | D14: 0.0026 | E14: 45362 | F14: 22332.65 | G14: =F14/F15-1 -> -0.0071531617 | H14: -0.0072
A15: 45358 | B15: 9673.15 | C15: =B15/B16-1 -> 0.0033295129 | D15: 0.0033 | E15: 45358 | F15: 22493.55 | G15: =F15/F16-1 -> 0.00086766738 | H15: 0.0009
A16: 45357 | B16: 9641.05 | C16: =B16/B17-1 -> -0.020054176 | D16: -0.0201 | E16: 45357 | F16: 22474.05 | G16: =F16/F17-1 -> 0.0052669717 | H16: 0.0053
A17: 45356 | B17: 9838.35 | C17: =B17/B18-1 -> -0.014035316 | D17: -0.014 | E17: 45356 | F17: 22356.3 | G17: =F17/F18-1 -> -0.0022003428 | H17: -0.0022
A18: 45355 | B18: 9978.4 | C18: =B18/B19-1 -> -0.012660357 | D18: -0.0127 | E18: 45355 | F18: 22405.6 | G18: =F18/F19-1 -> 0.0012154578 | H18: 0.0012
A19: 45353 | B19: 10106.35 | C19: =B19/B20-1 -> -0.0028760298 | D19: -0.0029 | E19: 45353 | F19: 22378.4 | G19: =F19/F20-1 -> 0.0017749426 | H19: 0.0018
A20: 45352 | B20: 10135.5 | C20: =B20/B21-1 -> 0.024574421 | D20: 0.0246 | E20: 45352 | F20: 22338.75 | G20: =F20/F21-1 -> 0.016192205 | H20: 0.0162
... A34: 45334 | B34: 9963.85 | C34: =B34/B35-1 -> 0.0018198728 | D34: 0.0018 | E34: 45334 | F34: 21616.05 | G34: =F34/F35-1 -> -0.0076414553 | H34: -0.0076
A35: 45331 | B35: 9945.75 | C35: =B35/B36-1 -> -0.0051912199 | D35: -0.0052 | E35: 45331 | F35: 21782.5 | G35: =F35/F36-1 -> 0.0029721958 | H35: 0.003 | L35: COST OF DEBT
A36: 45330 | B36: 9997.65 | C36: =B36/B37-1 -> -0.022378135 | D36: -0.0224 | E36: 45330 | F36: 21717.95 | G36: =F36/F37-1 -> -0.0096919815 | H36: -0.0097 | L36: Year | M36: 2021 | N36: 2022 | O36: 2023 | P36: 2024
A37: 45329 | B37: 10226.5 | C37: =B37/B38-1 -> 0.017688767 | D37: 0.0177 | E37: 45329 | F37: 21930.5 | G37: =F37/F38-1 -> 5.0160971e-05 | H37: 0.0001 | L37: Total Debt (Crores) | M37: =0.32*11754 -> 3761.28 | N37: =0.33*11548 -> 3810.84 | O37: =10790*0.17 -> 1834.3 | P37: =13282*0.06 -> 796.92
A38: 45328 | B38: 10048.75 | C38: =B38/B39-1 -> 0.013351687 | D38: 0.0134 | E38: 45328 | F38: 21929.4 | G38: =F38/F39-1 -> 0.007243348 | H38: 0.0072 | L38: Interest Paid(crores) | M38: 1259 | N38: 798 | O38: 756 | P38: 867
A39: 45327 | B39: 9916.35 | C39: =B39/B40-1 -> -0.018042194 | D39: -0.018 | E39: 45327 | F39: 21771.7 | G39: =F39/F40-1 -> -0.0037567837 | H39: -0.0038 | L39: Average Interest rate(%) | M39: =M38/M37 -> 0.33472648 | N39: =N38/N37 -> 0.20940265 | O39: =O38/O37 -> 0.41214632 | P39: =P38/P37 -> 1.0879386
A40: 45324 | B40: 10098.55 | C40: =B40/B41-1 -> 0.017763019 | D40: 0.0178 | E40: 45324 | F40: 21853.8 | G40: =F40/F41-1 -> 0.0072059159 | H40: 0.0072 | L40: Taxable income(Crores) | M40: 8060 | N40: 8293 | O40: 7262 | P40: 9388
A41: 45323 | B41: 9922.3 | C41: =B41/B42-1 -> -0.024101659 | D41: -0.0241 | E41: 45323 | F41: 21697.45 | G41: =F41/F42-1 -> -0.0013003033 | H41: -0.0013 | L41: Tax Paid (Crores) | M41: 2554 | N41: 1227 | O41: 2310 | P41: 2411 | S41: 0.086
A42: 45322 | B42: 10167.35 | C42: =B42/B43-1 -> 0.020449436 | D42: 0.0204 | E42: 45322 | F42: 21725.7 | G42: =F42/F43-1 -> 0.0094600434 | H42: 0.0095 | L42: Tax rate | M42: =M41/M40 -> 0.31687345 | N42: =N41/N40 -> 0.14795611 | O42: =O41/O40 -> 0.31809419 | P42: =P41/P40 -> 0.25681721 | R42: after tax cost of debt | S42: =S41*100 -> 8.6 | T42: %
A43: 45321 | B43: 9963.6 | C43: =B43/B44-1 -> -0.030216906 | D43: -0.0302 | E43: 45321 | F43: 21522.1 | G43: =F43/F44-1 -> -0.0099136979 | H43: -0.0099 | L43: After Tax cost of debt | M43: =M39*(1-M42) -> 0.22866054 | N43: =N39*(1-N42) -> 0.17842025 | O43: =O39*(1-O42) -> 0.28104497 | P43: =P39*(1-P42) -> 0.80853721 | R43: (average)
A44: 45320 | B44: 10274.05 | C44: =B44/B45-1 -> 0.030563678 | D44: 0.0306 | E44: 45320 | F44: 21737.6 | G44: =F44/F45-1 -> 0.018030591 | H44: 0.018 | L44: Total Equity (crores) | M44: 289 | N44: 289 | O44: 289 | P44: 289
A45: 45316 | B45: 9969.35 | C45: =B45/B46-1 -> -0.0021170112 | D45: -0.0021 | E45: 45316 | F45: 21352.6 | G45: =F45/F46-1 -> -0.0047240718 | H45: -0.0047 | L45: weight of debt | M45: =M37/(M37+M38) -> 0.74921718 | N45: =N37/(N37+N38) -> 0.82685448 | O45: =O37/(O37+O38) -> 0.70814191 | P45: =P37/(P37+P38) -> 0.4789413
A46: 45315 | B46: 9990.5 | C46: =B46/B47-1 -> 0.016224189 | D46: 0.0162 | E46: 45315 | F46: 21453.95 | G46: =F46/F47-1 -> 0.010130045 | H46: 0.0101 | L46: weight of debt(%) | M46: =M45*100 -> 74.921718 | N46: =N45*100 -> 82.685448 | O46: =O45*100 -> 70.814191 | P46: =P45*100 -> 47.89413
A47: 45314 | B47: 9831 | C47: =B47/B48-1 -> -0.016644328 | D47: -0.0166 | E47: 45314 | F47: 21238.8 | G47: =F47/F48-1 -> -0.01543682 | H47: -0.0154 | L47: weight of equity | M47: =1-M45 -> 0.25078282 | N47: =1-N45 -> 0.17314552 | O47: =1-O45 -> 0.29185809 | P47: =1-P45 -> 0.5210587
A48: 45311 | B48: 9997.4 | C48: =B48/B49-1 -> -0.0095406045 | D48: -0.0095 | E48: 45311 | F48: 21571.8 | G48: =F48/F49-1 -> -0.0023401658 | H48: -0.0023 | L48: weight of equity(%) | M48: =M47*100 -> 25.078282 | N48: =N47*100 -> 17.314552 | O48: =O47*100 -> 29.185809 | P48: =P47*100 -> 52.10587
A49: 45310 | B49: 10093.7 | C49: =B49/B50-1 -> 0.020364427 | D49: 0.0204 | E49: 45310 | F49: 21622.4 | G49: =F49/F50-1 -> 0.007461939 | H49: 0.0075 | L49: WACC(%) | M49: #REF! | N49: #REF! | O49: #REF! | P49: #REF!
A50: 45309 | B50: 9892.25 | C50: =B50/B51-1 -> 0.0038154577 | D50: 0.0038 | E50: 45309 | F50: 21462.25 | G50: =F50/F51-1 -> -0.0050853075 | H50: -0.0051 | L50: WACC(%) | M50: 0.242 | N50: 0.1963 | O50: 0.2813 | P50: 0.5341
A51: 45308 | B51: 9854.65 | C51: =B51/B52-1 -> -0.011530051 | D51: -0.0115 | E51: 45308 | F51: 21571.95 | G51: =F51/F52-1 -> -0.020894323 | H51: -0.0209 | L51: Average WACC | M51: =(M50+N50+O50+P50)/4 -> 0.313425
A52: 45307 | B52: 9969.6 | C52: =B52/B53-1 -> 0.0015118715 | D52: 0.0015 | E52: 45307 | F52: 22032.3 | G52: =F52/F53-1 -> -0.002948304 | H52: -0.0029 | L52: Average WACC | M52: =(M50+N50+O50+P50)/4 -> 0.313425
A53: 45306 | B53: 9954.55 | C53: =B53/B54-1 -> 0.01489532 | D53: 0.0149 | E53: 45306 | F53: 22097.45 | G53: =F53/F54-1 -> 0.0092671464 | H53: 0.0093
A54: 45303 | B54: 9808.45 | C54: =B54/B55-1 -> -0.01128981 | D54: -0.0113 | E54: 45303 | F54: 21894.55 | G54: =F54/F55-1 -> 0.01142642 | H54: 0.0114
A55: 45302 | B55: 9920.45 | C55: =B55/B56-1 -> 0.014755222 | D55: 0.0148 | E55: 45302 | F55: 21647.2 | G55: =F55/F56-1 -> 0.0013183031 | H55: 0.0013
A56: 45301 | B56: 9776.2 | C56: =B56/B57-1 -> -0.01241527 | D56: -0.0124 | E56: 45301 | F56: 21618.7 | G56: =F56/F57-1 -> 0.0034277333 | H56: 0.0034
A57: 45300 | B57: 9899.1 | C57: =B57/B58-1 -> -0.0035633399 | D57: -0.0036 | E57: 45300 | F57: 21544.85 | G57: =F57/F58-1 -> 0.0014805002 | H57: 0.0015
A58: 45299 | B58: 9934.5 | C58: =B58/B59-1 -> -0.0081419322 | D58: -0.0081 | E58: 45299 | F58: 21513 | G58: =F58/F59-1 -> -0.009110673 | H58: -0.0091
A59: 45296 | B59: 10016.05 | C59: =B59/B60-1 -> 0.00012481527 | D59: 0.0001 | E59: 45296 | F59: 21710.8 | G59: =F59/F60-1 -> 0.0024101281 | H59: 0.0024
A60: 45295 | B60: 10014.8 | C60: =B60/B61-1 -> -0.009568266 | D60: -0.0096 | E60: 45295 | F60: 21658.6 | G60: =F60/F61-1 -> 0.0065644701 | H60: 0.0066
A61: 45294 | B61: 10111.55 | C61: =B61/B62-1 -> -0.0091281468 | D61: -0.0091 | E61: 45294 | F61: 21517.35 | G61: =F61/F62-1 -> -0.0068518125 | H61: -0.0069
A62: 45293 | B62: 10204.7 | C62: =B62/B63-1 -> -0.024780199 | D62: -0.0248 | E62: 45293 | F62: 21665.8 | G62: =F62/F63-1 -> -0.0035001541 | H62: -0.0035
A63: 45292 | B63: 10464 | C63: =B63/B64-1 -> -0.0037179676 | D63: -0.0037 | E63: 45292 | F63: 21741.9 | G63: =F63/F64-1 -> 0.00048317182 | H63: 0.0005
A64: 45289 | B64: 10503.05 | C64: =B64/B65-1 -> 0.0073611924 | D64: 0.0074 | E64: 45289 | F64: 21731.4 | G64: =F64/F65-1 -> -0.0021718468 | H64: -0.0022
... A117: 45211 | B117: 8351.75 | C117: =B117/B118-1 -> 0.0010487834 | D117: 0.001 | E117: 45211 | F117: 19794 | G117: =F117/F118-1 -> -0.00087576061 | H117: -0.0009
A118: 45210 | B118: 8343 | C118: =B118/B119-1 -> 0.02263952 | D118: 0.0226 | E118: 45210 | F118: 19811.35 | G118: =F118/F119-1 -> 0.006170692 | H118: 0.0062 | L118: Variance of the stock | O118: Variance of the market
A119: 45209 | B119: 8158.3 | C119: =B119/B120-1 -> 0.0059432066 | D119: 0.0059 | E119: 45209 | F119: 19689.85 | G119: =F119/F120-1 -> 0.0090968028 | H119: 0.0091 | L119: =_xlfn.VAR.P(C9:C750) -> 0.0002095394 | O119: =_xlfn.VAR.P(G8:G750) -> 7.4920996e-05
A120: 45208 | B120: 8110.1 | C120: =B120/B121-1 -> -0.010414315 | D120: -0.0104 | E120: 45208 | F120: 19512.35 | G120: =F120/F121-1 -> -0.0071819269 | H120: -0.0072 | L120: =L119-Q121 -> 0.00020953923 | M120: UNSYSTEMATIC RISK | Q120: systematic Risk
A121: 45205 | B121: 8195.45 | C121: =B121/B122-1 -> 0.0022011752 | D121: 0.0022 | E121: 45205 | F121: 19653.5 | G121: =F121/F122-1 -> 0.0055127074 | H121: 0.0055 | Q121: =O119*H9^2 -> 1.6857224e-10
A122: 45204 | B122: 8177.45 | C122: =B122/B123-1 -> 0.0069697138 | D122: 0.007 | E122: 45204 | F122: 19545.75 | G122: =F122/F123-1 -> 0.0056415639 | H122: 0.0056
A123: 45203 | B123: 8120.85 | C123: =B123/B124-1 -> -0.022161615 | D123: -0.0222 | E123: 45203 | F123: 19436.1 | G123: =F123/F124-1 -> -0.0047442873 | H123: -0.0047
A124: 45202 | B124: 8304.9 | C124: =B124/B125-1 -> 0.0060631023 | D124: 0.0061 | E124: 45202 | F124: 19528.75 | G124: =F124/F125-1 -> -0.0055783851 | H124: -0.0056
A125: 45198 | B125: 8254.85 | C125: =B125/B126-1 -> 0.01232471 | D125: 0.0123 | E125: 45198 | F125: 19638.3 | G125: =F125/F126-1 -> 0.0058775172 | H125: 0.0059
A126: 45197 | B126: 8154.35 | C126: =B126/B127-1 -> -0.013113147 | D126: -0.0131 | E126: 45197 | F126: 19523.55 | G126: =F126/F127-1 -> -0.0097837085 | H126: -0.0098
A127: 45196 | B127: 8262.7 | C127: =B127/B128-1 -> 0.0041074749 | D127: 0.0041 | E127: 45196 | F127: 19716.45 | G127: =F127/F128-1 -> 0.0026316191 | H127: 0.0026
A128: 45195 | B128: 8228.9 | C128: =B128/B129-1 -> 0.0027662012 | D128: 0.0028 | E128: 45195 | F128: 19664.7 | G128: =F128/F129-1 -> -0.00050064677 | H128: -0.0005
A129: 45194 | B129: 8206.2 | C129: =B129/B130-1 -> 0.0022962113 | D129: 0.0023 | E129: 45194 | F129: 19674.55 | G129: =F129/F130-1 -> 1.5248358e-05 | H129: 0
A130: 45191 | B130: 8187.4 | C130: =B130/B131-1 -> -0.015174023 | D130: -0.0152 | E130: 45191 | F130: 19674.25 | G130: =F130/F131-1 -> -0.0034494374 | H130: -0.0034
A131: 45190 | B131: 8313.55 | C131: =B131/B132-1 -> -0.017095937 | D131: -0.0171 | E131: 45190 | F131: 19742.35 | G131: =F131/F132-1 -> -0.0079919001 | H131: -0.008
A132: 45189 | B132: 8458.15 | C132: =B132/B133-1 -> -0.019685906 | D132: -0.0197 | E132: 45189 | F132: 19901.4 | G132: =F132/F133-1 -> -0.011518231 | H132: -0.0115
A133: 45187 | B133: 8628 | C133: =B133/B134-1 -> -0.011497018 | D133: -0.0115 | E133: 45187 | F133: 20133.3 | G133: =F133/F134-1 -> -0.0029243748 | H133: -0.0029
... A137: 45181 | B137: 8571.65 | C137: =B137/B138-1 -> 0.012993843 | D137: 0.013 | E137: 45181 | F137: 19993.2 | G137: =F137/F138-1 -> -0.00015752875 | H137: -0.0002
A138: 45180 | B138: 8461.7 | C138: =B138/B139-1 -> 0.0036948954 | D138: 0.0037 | E138: 45180 | F138: 19996.35 | G138: =F138/F139-1 -> 0.0089001234 | H138: 0.0089 | L138: Dividend Yield
A139: 45177 | B139: 8430.55 | C139: =B139/B140-1 -> -0.0076043389 | D139: -0.0076 | E139: 45177 | F139: 19819.95 | G139: =F139/F140-1 -> 0.0047092698 | H139: 0.0047 | L139: Financial Year | M139: price of the stock (Rs) | N139: Dividend (Rs) | O139: Dividend Yield
A140: 45176 | B140: 8495.15 | C140: =B140/B141-1 -> -0.0049488135 | D140: -0.0049 | E140: 45176 | F140: 19727.05 | G140: =F140/F141-1 -> 0.0059150326 | H140: 0.0059 | L140: 2022 | M140: 7642.05 | N140: 37 | O140: =ultrattech!$N140/ultrattech!$M140 -> 0.0048416328
A141: 45175 | B141: 8537.4 | C141: =B141/B142-1 -> 0.0097636268 | D141: 0.0098 | E141: 45175 | F141: 19611.05 | G141: =F141/F142-1 -> 0.0018467527 | H141: 0.0018 | L141: 2023 | M141: 6651.3 | N141: 38 | O141: =ultrattech!$N141/ultrattech!$M141 -> 0.0057131689
A142: 45174 | B142: 8454.85 | C142: =B142/B143-1 -> -0.014879028 | D142: -0.0149 | E142: 45174 | F142: 19574.9 | G142: =F142/F143-1 -> 0.0023606161 | H142: 0.0024 | L142: 2024 | M142: 8821.5 | N142: 38 | O142: =ultrattech!$N142/ultrattech!$M142 -> 0.0043076574
A143: 45173 | B143: 8582.55 | C143: =B143/B144-1 -> 0.038747821 | D143: 0.0387 | E143: 45173 | F143: 19528.8 | G143: =F143/F144-1 -> 0.0048108339 | H143: 0.0048 | N143: AVERAGE | O143: =AVERAGE(O140:O142) -> 0.004954153
A144: 45170 | B144: 8262.4 | C144: =B144/B145-1 -> -0.0042241894 | D144: -0.0042 | E144: 45170 | F144: 19435.3 | G144: =F144/F145-1 -> 0.0094267106 | H144: 0.0094
A145: 45169 | B145: 8297.45 | C145: =B145/B146-1 -> 0.0038108142 | D145: 0.0038 | E145: 45169 | F145: 19253.8 | G145: =F145/F146-1 -> -0.0048404312 | H145: -0.0048
A146: 45168 | B146: 8265.95 | C146: =B146/B147-1 -> 0.0080795639 | D146: 0.0081 | E146: 45168 | F146: 19347.45 | G146: =F146/F147-1 -> 0.00024815628 | H146: 0.0002
A147: 45167 | B147: 8199.7 | C147: =B147/B148-1 -> 0.010107605 | D147: 0.0101 | E147: 45167 | F147: 19342.65 | G147: =F147/F148-1 -> 0.0018957788 | H147: 0.0019
A148: 45166 | B148: 8117.65 | C148: =B148/B149-1 -> 0.0057238786 | D148: 0.0057 | E148: 45166 | F148: 19306.05 | G148: =F148/F149-1 -> 0.0020891943 | H148: 0.0021
A149: 45163 | B149: 8071.45 | C149: =B149/B150-1 -> -0.017043379 | D149: -0.017 | E149: 45163 | F149: 19265.8 | G149: =F149/F150-1 -> -0.0062362341 | H149: -0.0062
A150: 45162 | B150: 8211.4 | C150: =B150/B151-1 -> 0.0060647643 | D150: 0.0061 | E150: 45162 | F150: 19386.7 | G150: =F150/F151-1 -> -0.0029469245 | H150: -0.0029
A151: 45161 | B151: 8161.9 | C151: =B151/B152-1 -> -0.0050710063 | D151: -0.0051 | E151: 45161 | F151: 19444 | G151: =F151/F152-1 -> 0.0024514795 | H151: 0.0025
A152: 45160 | B152: 8203.5 | C152: =B152/B153-1 -> -0.0019223048 | D152: -0.0019 | E152: 45160 | F152: 19396.45 | G152: =F152/F153-1 -> 0.0001469557 | H152: 0.0001
A153: 45159 | B153: 8219.3 | C153: =B153/B154-1 -> 0.00054170192 | D153: 0.0005 | E153: 45159 | F153: 19393.6 | G153: =F153/F154-1 -> 0.0043215615 | H153: 0.0043
A154: 45156 | B154: 8214.85 | C154: =B154/B155-1 -> 0.00091381506 | D154: 0.0009 | E154: 45156 | F154: 19310.15 | G154: =F154/F155-1 -> -0.0028453028 | H154: -0.0028
A155: 45155 | B155: 8207.35 | C155: =B155/B156-1 -> -0.0053987567 | D155: -0.0054 | E155: 45155 | F155: 19365.25 | G155: =F155/F156-1 -> -0.0051245826 | H155: -0.0051
... A743: 44291 | B743: 6795.8 | C743: =B743/B744-1 -> -0.014937272 | D743: -0.0149 | E743: 44291 | F743: 14637.8 | G743: =F743/F744-1 -> -0.015439873 | H743: -0.0154
A744: 44287 | B744: 6898.85 | D744: 0.0239 | E744: 44287 | F744: 14867.35 | H744: 0.012

Sheet AMBUJA
A1: Date | B1: Price | C1: change | D1: Change % | E1: Date | F1: Price | G1: change | H1: Change % | I1: beta | J1: beta(regression) | M1: =(F2/F744)^(1/3) -> 1.1451568
A2: 45379 | B2: 612.35 | C2: =B2/B3-1 -> 0.018038238 | D2: 0.018 | E2: 45379 | F2: 22326.9 | G2: =F2/F3-1 -> 0.0091870012 | H2: 0.0092 | I2: =_xlfn.COVARIANCE.P(C2:C743,G2:G743)/_xlfn.VAR.P(G2:G743) -> 1.056832 | J2: =_xlfn.COVARIANCE.P(D2:D743,H2:H743)/_xlfn.VAR.P(H2:H743) -> 1.0570445 | L2: Erm | M2: =M1-1 -> 0.14515679 | N2: Rf | O2: 0.065991
A3: 45378 | B3: 601.5 | C3: =B3/B4-1 -> 0.010839425 | D3: 0.0108 | E3: 45378 | F3: 22123.65 | G3: =F3/F4-1 -> 0.0054056633 | H3: 0.0054 | M3: 0.1452 | O3: =O2 -> 0.065991
A4: 45377 | B4: 595.05 | C4: =B4/B5-1 -> 0.0096716722 | D4: 0.0097 | E4: 45377 | F4: 22004.7 | G4: =F4/F5-1 -> -0.004165771 | H4: -0.0042
A5: 45373 | B5: 589.35 | C5: =B5/B6-1 -> 0.0036614441 | D5: 0.0037 | E5: 45373 | F5: 22096.75 | G5: =F5/F6-1 -> 0.0038524529 | H5: 0.0039 | L5: premium | M5: =M2-O3 -> 0.079165794
A6: 45372 | B6: 587.2 | C6: =B6/B7-1 -> 0.018825367 | D6: 0.0188 | E6: 45372 | F6: 22011.95 | G6: =F6/F7-1 -> 0.0079147034 | H6: 0.0079 | L6: beta premium | M6: =M5*I2 -> 0.083664946
A7: 45371 | B7: 576.35 | C7: =B7/B8-1 -> -0.0068068241 | D7: -0.0068 | E7: 45371 | F7: 21839.1 | G7: =F7/F8-1 -> 0.00099232495 | H7: 0.001 | L7: Ke(ERi) | M7: =M6+O3 -> 0.14965595 | N7: =M7*100 -> 14.965595
A8: 45370 | B8: 580.3 | C8: =B8/B9-1 -> -0.0074403489 | D8: -0.0074 | E8: 45370 | F8: 21817.45 | G8: =F8/F9-1 -> -0.010802196 | H8: -0.0108 | L8: (cost of equity) | N8: =M7 -> 0.14965595
A9: 45369 | B9: 584.65 | C9: =B9/B10-1 -> -0.026799834 | D9: -0.0268 | E9: 45369 | F9: 22055.7 | G9: =F9/F10-1 -> 0.0014688955 | H9: 0.0015
A10: 45366 | B10: 600.75 | C10: =B10/B11-1 -> 0.031419006 | D10: 0.0314 | E10: 45366 | F10: 22023.35 | G10: =F10/F11-1 -> -0.0055674334 | H10: -0.0056
A11: 45365 | B11: 582.45 | C11: =B11/B12-1 -> 0.041484131 | D11: 0.0415 | E11: 45365 | F11: 22146.65 | G11: =F11/F12-1 -> 0.0067711624 | H11: 0.0068
A12: 45364 | B12: 559.25 | C12: =B12/B13-1 -> -0.048166114 | D12: -0.0482 | E12: 45364 | F12: 21997.7 | G12: =F12/F13-1 -> -0.015132725 | H12: -0.0151
A13: 45363 | B13: 587.55 | C13: =B13/B14-1 -> -0.024084378 | D13: -0.0241 | E13: 45363 | F13: 22335.7 | G13: =F13/F14-1 -> 0.00013657134 | H13: 0.0001
A14: 45362 | B14: 602.05 | C14: =B14/B15-1 -> -0.0018237586 | D14: -0.0018 | E14: 45362 | F14: 22332.65 | G14: =F14/F15-1 -> -0.0071531617 | H14: -0.0072
A15: 45358 | B15: 603.15 | C15: =B15/B16-1 -> 0.0081063012 | D15: 0.0081 | E15: 45358 | F15: 22493.55 | G15: =F15/F16-1 -> 0.00086766738 | H15: 0.0009
A16: 45357 | B16: 598.3 | C16: =B16/B17-1 -> -0.024139618 | D16: -0.0241 | E16: 45357 | F16: 22474.05 | G16: =F16/F17-1 -> 0.0052669717 | H16: 0.0053
A17: 45356 | B17: 613.1 | C17: =B17/B18-1 -> -0.006562424 | D17: -0.0066 | E17: 45356 | F17: 22356.3 | G17: =F17/F18-1 -> -0.0022003428 | H17: -0.0022
A18: 45355 | B18: 617.15 | C18: =B18/B19-1 -> -0.0029081509 | D18: -0.0029 | E18: 45355 | F18: 22405.6 | G18: =F18/F19-1 -> 0.0012154578 | H18: 0.0012
A19: 45353 | B19: 618.95 | C19: =B19/B20-1 -> 0.0021858808 | D19: 0.0022 | E19: 45353 | F19: 22378.4 | G19: =F19/F20-1 -> 0.0017749426 | H19: 0.0018
A20: 45352 | B20: 617.6 | C20: =B20/B21-1 -> 0.019310117 | D20: 0.0193 | E20: 45352 | F20: 22338.75 | G20: =F20/F21-1 -> 0.016192205 | H20: 0.0162
... A34: 45334 | B34: 563.5 | C34: =B34/B35-1 -> -0.022040958 | D34: -0.022 | E34: 45334 | F34: 21616.05 | G34: =F34/F35-1 -> -0.0076414553 | H34: -0.0076
A35: 45331 | B35: 576.2 | C35: =B35/B36-1 -> 0.022809976 | D35: 0.0228 | E35: 45331 | F35: 21782.5 | G35: =F35/F36-1 -> 0.0029721958 | H35: 0.003 | L35: COST OF DEBT
A36: 45330 | B36: 563.35 | C36: =B36/B37-1 -> -0.0085357269 | D36: -0.0085 | E36: 45330 | F36: 21717.95 | G36: =F36/F37-1 -> -0.0096919815 | H36: -0.0097 | L36: Year | M36: 2021 | N36: 2022 | O36: 2023
A37: 45329 | B37: 568.2 | C37: =B37/B38-1 -> 0.0028238616 | D37: 0.0028 | E37: 45329 | F37: 21930.5 | G37: =F37/F38-1 -> 5.0160971e-05 | H37: 0.0001 | L37: Total Debt (Crores) | M37: 3937 | N37: 236.91 | O37: 1099.55
A38: 45328 | B38: 566.6 | C38: =B38/B39-1 -> 0.020900901 | D38: 0.0209 | E38: 45328 | F38: 21929.4 | G38: =F38/F39-1 -> 0.007243348 | H38: 0.0072 | L38: Interest Paid(crores) | M38: 90.94 | N38: 127.97 | O38: 162.25
A39: 45327 | B39: 555 | C39: =B39/B40-1 -> -0.0043057051 | D39: -0.0043 | E39: 45327 | F39: 21771.7 | G39: =F39/F40-1 -> -0.0037567837 | H39: -0.0038 | L39: Average Interest rate(%) | M39: =M38/M37 -> 0.023098806 | N39: =N38/N37 -> 0.54016293 | O39: =O38/O37 -> 0.14756037
A40: 45324 | B40: 557.4 | C40: =B40/B41-1 -> -0.013538625 | D40: -0.0135 | E40: 45324 | F40: 21853.8 | G40: =F40/F41-1 -> 0.0072059159 | H40: 0.0072 | L40: Taxable income(Crores) | M40: 2785.25 | N40: 3055.05 | O40: 3107.45
A41: 45323 | B41: 565.05 | C41: =B41/B42-1 -> 0.0084776013 | D41: 0.0085 | E41: 45323 | F41: 21697.45 | G41: =F41/F42-1 -> -0.0013003033 | H41: -0.0013 | L41: Tax Paid (Crores) | M41: 704.71 | N41: 501.56 | O41: 772.76 | R41: 0.086
A42: 45322 | B42: 560.3 | C42: =B42/B43-1 -> -0.018481212 | D42: -0.0185 | E42: 45322 | F42: 21725.7 | G42: =F42/F43-1 -> 0.0094600434 | H42: 0.0095 | L42: Tax rate | M42: =M41/M40 -> 0.25301499 | N42: =N41/N40 -> 0.16417407 | O42: =O41/O40 -> 0.24867979 | Q42: after tax cost of debt | R42: =R41*100 -> 8.6 | S42: %
A43: 45321 | B43: 570.85 | C43: =B43/B44-1 -> -0.0056610347 | D43: -0.0057 | E43: 45321 | F43: 21522.1 | G43: =F43/F44-1 -> -0.0099136979 | H43: -0.0099 | L43: After Tax cost of debt | M43: =M39*(1-M42) -> 0.017254462 | N43: =N39*(1-N42) -> 0.45148218 | O43: =O39*(1-O42) -> 0.11086509 | Q43: (average)
A44: 45320 | B44: 574.1 | C44: =B44/B45-1 -> 0.024904044 | D44: 0.0249 | E44: 45320 | F44: 21737.6 | G44: =F44/F45-1 -> 0.018030591 | H44: 0.018 | L44: Total Equity (crores) | M44: 22207 | N44: 289 | O44: 289
A45: 45316 | B45: 560.15 | C45: =B45/B46-1 -> 0.061996398 | D45: 0.062 | E45: 45316 | F45: 21352.6 | G45: =F45/F46-1 -> -0.0047240718 | H45: -0.0047 | L45: weight of debt | M45: =M37/(M37+M38) -> 0.9774227 | N45: =N37/(N37+N38) -> 0.64928196 | O45: =O37/(O37+O38) -> 0.87141385
A46: 45315 | B46: 527.45 | C46: =B46/B47-1 -> 0.0045709932 | D46: 0.0046 | E46: 45315 | F46: 21453.95 | G46: =F46/F47-1 -> 0.010130045 | H46: 0.0101 | L46: weight of debt(%) | M46: =M45*100 -> 97.74227 | N46: =N45*100 -> 64.928196 | O46: =O45*100 -> 87.141385
A47: 45314 | B47: 525.05 | C47: =B47/B48-1 -> -0.029033749 | D47: -0.029 | E47: 45314 | F47: 21238.8 | G47: =F47/F48-1 -> -0.01543682 | H47: -0.0154 | L47: weight of equity | M47: =1-M45 -> 0.022577298 | N47: =1-N45 -> 0.35071804 | O47: =1-O45 -> 0.12858615
A48: 45311 | B48: 540.75 | C48: =B48/B49-1 -> 0.006795755 | D48: 0.0068 | E48: 45311 | F48: 21571.8 | G48: =F48/F49-1 -> -0.0023401658 | H48: -0.0023 | L48: weight of equity(%) | M48: =M47*100 -> 2.2577298 | N48: =N47*100 -> 35.071804 | O48: =O47*100 -> 12.858615
A49: 45310 | B49: 537.1 | C49: =B49/B50-1 -> 0.024706668 | D49: 0.0247 | E49: 45310 | F49: 21622.4 | G49: =F49/F50-1 -> 0.007461939 | H49: 0.0075 | L49: WACC(%) | M49: #REF! | N49: #REF! | O49: #REF!
A50: 45309 | B50: 524.15 | C50: =B50/B51-1 -> 0.0069157622 | D50: 0.0069 | E50: 45309 | F50: 21462.25 | G50: =F50/F51-1 -> -0.0050853075 | H50: -0.0051 | L50: WACC(%) | M50: 0.0232 | N50: 0.392 | O50: 0.1328
A51: 45308 | B51: 520.55 | C51: =B51/B52-1 -> -0.015415169 | D51: -0.0154 | E51: 45308 | F51: 21571.95 | G51: =F51/F52-1 -> -0.020894323 | H51: -0.0209 | L51: Average WACC | M51: =(M50+N50+O50)/3 -> 0.18266667
A52: 45307 | B52: 528.7 | C52: =B52/B53-1 -> -0.0051745225 | D52: -0.0052 | E52: 45307 | F52: 22032.3 | G52: =F52/F53-1 -> -0.002948304 | H52: -0.0029 | L52: Average WACC | M52: 0.1827
A53: 45306 | B53: 531.45 | C53: =B53/B54-1 -> -0.0017843727 | D53: -0.0018 | E53: 45306 | F53: 22097.45 | G53: =F53/F54-1 -> 0.0092671464 | H53: 0.0093
A54: 45303 | B54: 532.4 | C54: =B54/B55-1 -> -0.010868555 | D54: -0.0109 | E54: 45303 | F54: 21894.55 | G54: =F54/F55-1 -> 0.01142642 | H54: 0.0114
A55: 45302 | B55: 538.25 | C55: =B55/B56-1 -> 0.022997244 | D55: 0.023 | E55: 45302 | F55: 21647.2 | G55: =F55/F56-1 -> 0.0013183031 | H55: 0.0013
A56: 45301 | B56: 526.15 | C56: =B56/B57-1 -> 0.0018088347 | D56: 0.0018 | E56: 45301 | F56: 21618.7 | G56: =F56/F57-1 -> 0.0034277333 | H56: 0.0034
A57: 45300 | B57: 525.2 | C57: =B57/B58-1 -> -0.0094304036 | D57: -0.0094 | E57: 45300 | F57: 21544.85 | G57: =F57/F58-1 -> 0.0014805002 | H57: 0.0015
A58: 45299 | B58: 530.2 | C58: =B58/B59-1 -> -0.022402508 | D58: -0.0224 | E58: 45299 | F58: 21513 | G58: =F58/F59-1 -> -0.009110673 | H58: -0.0091
A59: 45296 | B59: 542.35 | C59: =B59/B60-1 -> -0.012922013 | D59: -0.0129 | E59: 45296 | F59: 21710.8 | G59: =F59/F60-1 -> 0.0024101281 | H59: 0.0024
A60: 45295 | B60: 549.45 | C60: =B60/B61-1 -> 0.024902071 | D60: 0.0249 | E60: 45295 | F60: 21658.6 | G60: =F60/F61-1 -> 0.0065644701 | H60: 0.0066
A61: 45294 | B61: 536.1 | C61: =B61/B62-1 -> 0.0097946883 | D61: 0.0098 | E61: 45294 | F61: 21517.35 | G61: =F61/F62-1 -> -0.0068518125 | H61: -0.0069
A62: 45293 | B62: 530.9 | C62: =B62/B63-1 -> -0.0063634662 | D62: -0.0064 | E62: 45293 | F62: 21665.8 | G62: =F62/F63-1 -> -0.0035001541 | H62: -0.0035
A63: 45292 | B63: 534.3 | C63: =B63/B64-1 -> 0.025724707 | D63: 0.0257 | E63: 45292 | F63: 21741.9 | G63: =F63/F64-1 -> 0.00048317182 | H63: 0.0005
A64: 45289 | B64: 520.9 | C64: =B64/B65-1 -> 0.012931454 | D64: 0.0129 | E64: 45289 | F64: 21731.4 | G64: =F64/F65-1 -> -0.0021718468 | H64: -0.0022
... A117: 45211 | B117: 445.6 | C117: =B117/B118-1 -> 0.0011233431 | D117: 0.0011 | E117: 45211 | F117: 19794 | G117: =F117/F118-1 -> -0.00087576061 | H117: -0.0009
A118: 45210 | B118: 445.1 | C118: =B118/B119-1 -> 0.018069533 | D118: 0.0181 | E118: 45210 | F118: 19811.35 | G118: =F118/F119-1 -> 0.006170692 | H118: 0.0062 | L118: Variance of the stock | O118: Variance of the market
A119: 45209 | B119: 437.2 | C119: =B119/B120-1 -> 0.016271502 | D119: 0.0163 | E119: 45209 | F119: 19689.85 | G119: =F119/F120-1 -> 0.0090968028 | H119: 0.0091 | L119: =_xlfn.VAR.P(C9:C750) -> 0.00048260593 | O119: =_xlfn.VAR.P(G8:G750) -> 7.4920996e-05
A120: 45208 | B120: 430.2 | C120: =B120/B121-1 -> -0.012623365 | D120: -0.0126 | E120: 45208 | F120: 19512.35 | G120: =F120/F121-1 -> -0.0071819269 | H120: -0.0072 | L120: =L119-Q121 -> 0.00048260576 | M120: UNSYSTEMATIC RISK | Q120: systematic Risk
A121: 45205 | B121: 435.7 | C121: =B121/B122-1 -> 0.0065842671 | D121: 0.0066 | E121: 45205 | F121: 19653.5 | G121: =F121/F122-1 -> 0.0055127074 | H121: 0.0055 | Q121: =O119*H9^2 -> 1.6857224e-10
A122: 45204 | B122: 432.85 | C122: =B122/B123-1 -> 0.0074479227 | D122: 0.0074 | E122: 45204 | F122: 19545.75 | G122: =F122/F123-1 -> 0.0056415639 | H122: 0.0056
A123: 45203 | B123: 429.65 | C123: =B123/B124-1 -> -0.0059000463 | D123: -0.0059 | E123: 45203 | F123: 19436.1 | G123: =F123/F124-1 -> -0.0047442873 | H123: -0.0047
A124: 45202 | B124: 432.2 | C124: =B124/B125-1 -> 0.017419962 | D124: 0.0174 | E124: 45202 | F124: 19528.75 | G124: =F124/F125-1 -> -0.0055783851 | H124: -0.0056
A125: 45198 | B125: 424.8 | C125: =B125/B126-1 -> 0.011669445 | D125: 0.0117 | E125: 45198 | F125: 19638.3 | G125: =F125/F126-1 -> 0.0058775172 | H125: 0.0059
A126: 45197 | B126: 419.9 | C126: =B126/B127-1 -> -0.024509235 | D126: -0.0245 | E126: 45197 | F126: 19523.55 | G126: =F126/F127-1 -> -0.0097837085 | H126: -0.0098
A127: 45196 | B127: 430.45 | C127: =B127/B128-1 -> 0.001628854 | D127: 0.0016 | E127: 45196 | F127: 19716.45 | G127: =F127/F128-1 -> 0.0026316191 | H127: 0.0026
A128: 45195 | B128: 429.75 | C128: =B128/B129-1 -> 0.016197683 | D128: 0.0162 | E128: 45195 | F128: 19664.7 | G128: =F128/F129-1 -> -0.00050064677 | H128: -0.0005
A129: 45194 | B129: 422.9 | C129: =B129/B130-1 -> 0.0046323791 | D129: 0.0046 | E129: 45194 | F129: 19674.55 | G129: =F129/F130-1 -> 1.5248358e-05 | H129: 0
A130: 45191 | B130: 420.95 | C130: =B130/B131-1 -> -0.012086365 | D130: -0.0121 | E130: 45191 | F130: 19674.25 | G130: =F130/F131-1 -> -0.0034494374 | H130: -0.0034
A131: 45190 | B131: 426.1 | C131: =B131/B132-1 -> -0.0047880416 | D131: -0.0048 | E131: 45190 | F131: 19742.35 | G131: =F131/F132-1 -> -0.0079919001 | H131: -0.008
A132: 45189 | B132: 428.15 | C132: =B132/B133-1 -> -0.019466392 | D132: -0.0195 | E132: 45189 | F132: 19901.4 | G132: =F132/F133-1 -> -0.011518231 | H132: -0.0115
A133: 45187 | B133: 436.65 | C133: =B133/B134-1 -> -0.018874284 | D133: -0.0189 | E133: 45187 | F133: 20133.3 | G133: =F133/F134-1 -> -0.0029243748 | H133: -0.0029
... A137: 45181 | B137: 445 | C137: =B137/B138-1 -> -0.013084941 | D137: -0.0131 | E137: 45181 | F137: 19993.2 | G137: =F137/F138-1 -> -0.00015752875 | H137: -0.0002
A138: 45180 | B138: 450.9 | C138: =B138/B139-1 -> 0.026639344 | D138: 0.0266 | E138: 45180 | F138: 19996.35 | G138: =F138/F139-1 -> 0.0089001234 | H138: 0.0089 | L138: Dividend Yield
A139: 45177 | B139: 439.2 | C139: =B139/B140-1 -> -0.00056889293 | D139: -0.0006 | E139: 45177 | F139: 19819.95 | G139: =F139/F140-1 -> 0.0047092698 | H139: 0.0047 | L139: Financial Year | M139: price of the stock (Rs) | N139: Dividend (Rs) | O139: Dividend Yield
A140: 45176 | B140: 439.45 | C140: =B140/B141-1 -> 0.0038834951 | D140: 0.0039 | E140: 45176 | F140: 19727.05 | G140: =F140/F141-1 -> 0.0059150326 | H140: 0.0059 | L140: 2022 | M140: 360.7 | N140: 6.3 | O140: =AMBUJA!$N140/AMBUJA!$M140 -> 0.017466038
A141: 45175 | B141: 437.75 | C141: =B141/B142-1 -> -0.005565652 | D141: -0.0056 | E141: 45175 | F141: 19611.05 | G141: =F141/F142-1 -> 0.0018467527 | H141: 0.0018 | L141: 2023 | M141: 427.3 | N141: 2.5 | O141: =AMBUJA!$N141/AMBUJA!$M141 -> 0.0058506904
A142: 45174 | B142: 440.2 | C142: =B142/B143-1 -> -0.0021534625 | D142: -0.0022 | E142: 45174 | F142: 19574.9 | G142: =F142/F143-1 -> 0.0023606161 | H142: 0.0024 | L142: 2024 | M142: 612.45 | N142: 0 | O142: =AMBUJA!$N142/AMBUJA!$M142 -> 0
A143: 45173 | B143: 441.15 | C143: =B143/B144-1 -> 0.016708919 | D143: 0.0167 | E143: 45173 | F143: 19528.8 | G143: =F143/F144-1 -> 0.0048108339 | H143: 0.0048 | N143: AVERAGE | O143: =AVERAGE(O140:O142) -> 0.0077722429
A144: 45170 | B144: 433.9 | C144: =B144/B145-1 -> 0.012838469 | D144: 0.0128 | E144: 45170 | F144: 19435.3 | G144: =F144/F145-1 -> 0.0094267106 | H144: 0.0094
A145: 45169 | B145: 428.4 | C145: =B145/B146-1 -> -0.035243779 | D145: -0.0352 | E145: 45169 | F145: 19253.8 | G145: =F145/F146-1 -> -0.0048404312 | H145: -0.0048
A146: 45168 | B146: 444.05 | C146: =B146/B147-1 -> 0.0064596555 | D146: 0.0065 | E146: 45168 | F146: 19347.45 | G146: =F146/F147-1 -> 0.00024815628 | H146: 0.0002
A147: 45167 | B147: 441.2 | C147: =B147/B148-1 -> 0.0053549049 | D147: 0.0054 | E147: 45167 | F147: 19342.65 | G147: =F147/F148-1 -> 0.0018957788 | H147: 0.0019
A148: 45166 | B148: 438.85 | C148: =B148/B149-1 -> 0.0097791072 | D148: 0.0098 | E148: 45166 | F148: 19306.05 | G148: =F148/F149-1 -> 0.0020891943 | H148: 0.0021
A149: 45163 | B149: 434.6 | C149: =B149/B150-1 -> -0.03196347 | D149: -0.032 | E149: 45163 | F149: 19265.8 | G149: =F149/F150-1 -> -0.0062362341 | H149: -0.0062
A150: 45162 | B150: 448.95 | C150: =B150/B151-1 -> -0.0095962938 | D150: -0.0096 | E150: 45162 | F150: 19386.7 | G150: =F150/F151-1 -> -0.0029469245 | H150: -0.0029
A151: 45161 | B151: 453.3 | C151: =B151/B152-1 -> -0.022639069 | D151: -0.0226 | E151: 45161 | F151: 19444 | G151: =F151/F152-1 -> 0.0024514795 | H151: 0.0025
A152: 45160 | B152: 463.8 | C152: =B152/B153-1 -> -0.003116604 | D152: -0.0031 | E152: 45160 | F152: 19396.45 | G152: =F152/F153-1 -> 0.0001469557 | H152: 0.0001
A153: 45159 | B153: 465.25 | C153: =B153/B154-1 -> 0.026928595 | D153: 0.0269 | E153: 45159 | F153: 19393.6 | G153: =F153/F154-1 -> 0.0043215615 | H153: 0.0043
A154: 45156 | B154: 453.05 | C154: =B154/B155-1 -> 0.015807175 | D154: 0.0158 | E154: 45156 | F154: 19310.15 | G154: =F154/F155-1 -> -0.0028453028 | H154: -0.0028
A155: 45155 | B155: 446 | C155: =B155/B156-1 -> 0.020128088 | D155: 0.0201 | E155: 45155 | F155: 19365.25 | G155: =F155/F156-1 -> -0.0051245826 | H155: -0.0051
... A743: 44291 | B743: 306.05 | C743: =B743/B744-1 -> -0.015916399 | D743: -0.0159 | E743: 44291 | F743: 14637.8 | G743: =F743/F744-1 -> -0.015439873 | H743: -0.0154
A744: 44287 | B744: 311 | D744: 0.007 | E744: 44287 | F744: 14867.35 | H744: 0.012

Sheet ACC
A1: Date | B1: Price | C1: change | D1: Change % | E1: Date | F1: Price | G1: change | H1: Change % | I1: beta | J1: beta(regression) | M1: =(F2/F744)^(1/3) -> 1.1451568
A2: 45379 | B2: 2491.7 | C2: =B2/B3-1 -> 0.015321299 | D2: 0.0153 | E2: 45379 | F2: 22326.9 | G2: =F2/F3-1 -> 0.0091870012 | H2: 0.0092 | I2: =_xlfn.COVARIANCE.P(C2:C743,G2:G743)/_xlfn.VAR.P(G2:G743) -> 1.0107792 | J2: =_xlfn.COVARIANCE.P(D2:D743,H2:H743)/_xlfn.VAR.P(H2:H743) -> 1.010716 | L2: Erm | M2: =M1-1 -> 0.14515679 | N2: Rf | O2: 0.065991
A3: 45378 | B3: 2454.1 | C3: =B3/B4-1 -> 0.0016734694 | D3: 0.0017 | E3: 45378 | F3: 22123.65 | G3: =F3/F4-1 -> 0.0054056633 | H3: 0.0054 | M3: 0.1452 | O3: =O2 -> 0.065991
A4: 45377 | B4: 2450 | C4: =B4/B5-1 -> 0.0027627136 | D4: 0.0028 | E4: 45377 | F4: 22004.7 | G4: =F4/F5-1 -> -0.004165771 | H4: -0.0042
A5: 45373 | B5: 2443.25 | C5: =B5/B6-1 -> 0.001804129 | D5: 0.0018 | E5: 45373 | F5: 22096.75 | G5: =F5/F6-1 -> 0.0038524529 | H5: 0.0039 | L5: premium | M5: =M2-O3 -> 0.079165794
A6: 45372 | B6: 2438.85 | C6: =B6/B7-1 -> 0.017162281 | D6: 0.0172 | E6: 45372 | F6: 22011.95 | G6: =F6/F7-1 -> 0.0079147034 | H6: 0.0079 | L6: beta premium | M6: =M5*I2 -> 0.080019134
A7: 45371 | B7: 2397.7 | C7: =B7/B8-1 -> -0.0023716402 | D7: -0.0024 | E7: 45371 | F7: 21839.1 | G7: =F7/F8-1 -> 0.00099232495 | H7: 0.001 | L7: Ke(ERi) | M7: =M6+O3 -> 0.14601013 | N7: =M7*100 -> 14.601013
A8: 45370 | B8: 2403.4 | C8: =B8/B9-1 -> -0.01562532 | D8: -0.0156 | E8: 45370 | F8: 21817.45 | G8: =F8/F9-1 -> -0.010802196 | H8: -0.0108 | L8: (cost of equity) | N8: =M7 -> 0.14601013
A9: 45369 | B9: 2441.55 | C9: =B9/B10-1 -> -0.024531053 | D9: -0.0245 | E9: 45369 | F9: 22055.7 | G9: =F9/F10-1 -> 0.0014688955 | H9: 0.0015
A10: 45366 | B10: 2502.95 | C10: =B10/B11-1 -> 0.008400145 | D10: 0.0084 | E10: 45366 | F10: 22023.35 | G10: =F10/F11-1 -> -0.0055674334 | H10: -0.0056
A11: 45365 | B11: 2482.1 | C11: =B11/B12-1 -> 0.038926793 | D11: 0.0389 | E11: 45365 | F11: 22146.65 | G11: =F11/F12-1 -> 0.0067711624 | H11: 0.0068
A12: 45364 | B12: 2389.1 | C12: =B12/B13-1 -> -0.067340725 | D12: -0.0673 | E12: 45364 | F12: 21997.7 | G12: =F12/F13-1 -> -0.015132725 | H12: -0.0151
A13: 45363 | B13: 2561.6 | C13: =B13/B14-1 -> -0.030394792 | D13: -0.0304 | E13: 45363 | F13: 22335.7 | G13: =F13/F14-1 -> 0.00013657134 | H13: 0.0001
A14: 45362 | B14: 2641.9 | C14: =B14/B15-1 -> 0.0011747764 | D14: 0.0012 | E14: 45362 | F14: 22332.65 | G14: =F14/F15-1 -> -0.0071531617 | H14: -0.0072
A15: 45358 | B15: 2638.8 | C15: =B15/B16-1 -> -0.0012112036 | D15: -0.0012 | E15: 45358 | F15: 22493.55 | G15: =F15/F16-1 -> 0.00086766738 | H15: 0.0009
A16: 45357 | B16: 2642 | C16: =B16/B17-1 -> -0.010023419 | D16: -0.01 | E16: 45357 | F16: 22474.05 | G16: =F16/F17-1 -> 0.0052669717 | H16: 0.0053
A17: 45356 | B17: 2668.75 | C17: =B17/B18-1 -> -0.0099790403 | D17: -0.01 | E17: 45356 | F17: 22356.3 | G17: =F17/F18-1 -> -0.0022003428 | H17: -0.0022
A18: 45355 | B18: 2695.65 | C18: =B18/B19-1 -> -0.0025531443 | D18: -0.0026 | E18: 45355 | F18: 22405.6 | G18: =F18/F19-1 -> 0.0012154578 | H18: 0.0012
A19: 45353 | B19: 2702.55 | C19: =B19/B20-1 -> 0.0026340685 | D19: 0.0026 | E19: 45353 | F19: 22378.4 | G19: =F19/F20-1 -> 0.0017749426 | H19: 0.0018
A20: 45352 | B20: 2695.45 | C20: =B20/B21-1 -> 0.025158788 | D20: 0.0252 | E20: 45352 | F20: 22338.75 | G20: =F20/F21-1 -> 0.016192205 | H20: 0.0162
... A34: 45334 | B34: 2636.35 | C34: =B34/B35-1 -> 0.0031582352 | D34: 0.0032 | E34: 45334 | F34: 21616.05 | G34: =F34/F35-1 -> -0.0076414553 | H34: -0.0076
A35: 45331 | B35: 2628.05 | C35: =B35/B36-1 -> 0.04667742 | D35: 0.0467 | E35: 45331 | F35: 21782.5 | G35: =F35/F36-1 -> 0.0029721958 | H35: 0.003 | L35: COST OF DEBT
A36: 45330 | B36: 2510.85 | C36: =B36/B37-1 -> 0.002115304 | D36: 0.0021 | E36: 45330 | F36: 21717.95 | G36: =F36/F37-1 -> -0.0096919815 | H36: -0.0097 | L36: Year | M36: 2021 | N36: 2022 | O36: 2023 | P36: 2024
A37: 45329 | B37: 2505.55 | C37: =B37/B38-1 -> -0.0089785425 | D37: -0.009 | E37: 45329 | F37: 21930.5 | G37: =F37/F38-1 -> 5.0160971e-05 | H37: 0.0001 | L37: Total Debt (Crores) | M37: 1255.88 | N37: 1318.1 | O37: 1530.4 | P37: 3548.5
A38: 45328 | B38: 2528.25 | C38: =B38/B39-1 -> 0.016913362 | D38: 0.0169 | E38: 45328 | F38: 21929.4 | G38: =F38/F39-1 -> 0.007243348 | H38: 0.0072 | L38: Interest Paid(crores) | M38: 57.04 | N38: 54.63 | O38: 77.18 | P38: 153.79
A39: 45327 | B39: 2486.2 | C39: =B39/B40-1 -> -0.0053011663 | D39: -0.0053 | E39: 45327 | F39: 21771.7 | G39: =F39/F40-1 -> -0.0037567837 | H39: -0.0038 | L39: Average Interest rate(%) | M39: =M38/M37 -> 0.045418352 | N39: =N38/N37 -> 0.041446021 | O39: =O38/O37 -> 0.05043126 | P39: =P38/P37 -> 0.043339439
A40: 45324 | B40: 2499.45 | C40: =B40/B41-1 -> -0.012075099 | D40: -0.0121 | E40: 45324 | F40: 21853.8 | G40: =F40/F41-1 -> 0.0072059159 | H40: 0.0072 | L40: Taxable income(Crores) | M40: 25063.8 | N40: 871.25 | O40: 1182.13 | P40: 2519.08
A41: 45323 | B41: 2530 | C41: =B41/B42-1 -> -0.0056204064 | D41: -0.0056 | E41: 45323 | F41: 21697.45 | G41: =F41/F42-1 -> -0.0013003033 | H41: -0.0013 | L41: Tax Paid (Crores) | M41: 6432.8 | N41: 2217 | O41: 1814.4 | P41: 4227.7 | S41: 0.086
A42: 45322 | B42: 2544.3 | C42: =B42/B43-1 -> 0.012394803 | D42: 0.0124 | E42: 45322 | F42: 21725.7 | G42: =F42/F43-1 -> 0.0094600434 | H42: 0.0095 | L42: Tax rate | M42: =M41/M40 -> 0.25665701 | N42: =N41/N40 -> 2.5446198 | O42: =O41/O40 -> 1.5348566 | P42: =P41/P40 -> 1.6782714 | R42: after tax cost of debt | S42: =S41*100 -> 8.6 | T42: %
A43: 45321 | B43: 2513.15 | C43: =B43/B44-1 -> 0.0081230695 | D43: 0.0081 | E43: 45321 | F43: 21522.1 | G43: =F43/F44-1 -> -0.0099136979 | H43: -0.0099 | L43: After Tax cost of debt | M43: =M39*(1-M42) -> 0.033761414 | N43: =N39*(1-N42) -> -0.064018344 | O43: =O39*(1-O42) -> -0.026973491 | P43: =P39*(1-P42) -> -0.029395904 | R43: (average)
A44: 45320 | B44: 2492.9 | C44: =B44/B45-1 -> 0.010232407 | D44: 0.0102 | E44: 45320 | F44: 21737.6 | G44: =F44/F45-1 -> 0.018030591 | H44: 0.018 | L44: Total Equity (crores) | M44: 143121.8 | N44: 138895 | O44: 14149.5 | P44: 163333.1
A45: 45316 | B45: 2467.65 | C45: =B45/B46-1 -> 0.10133446 | D45: 0.1013 | E45: 45316 | F45: 21352.6 | G45: =F45/F46-1 -> -0.0047240718 | H45: -0.0047 | L45: weight of debt | M45: =M37/(M37+M44) -> 0.0086985745 | N45: =N37/(N37+N44) -> 0.0094006908 | O45: =O37/(O37+O44) -> 0.097602663 | P45: =P37/(P37+P44) -> 0.021263578
A46: 45315 | B46: 2240.6 | C46: =B46/B47-1 -> 0.014787473 | D46: 0.0148 | E46: 45315 | F46: 21453.95 | G46: =F46/F47-1 -> 0.010130045 | H46: 0.0101 | L46: weight of debt(%) | M46: =M45*100 -> 0.86985745 | N46: =N45*100 -> 0.94006908 | O46: =O45*100 -> 9.7602663 | P46: =P45*100 -> 2.1263578
A47: 45314 | B47: 2207.95 | C47: =B47/B48-1 -> -0.035871796 | D47: -0.0359 | E47: 45314 | F47: 21238.8 | G47: =F47/F48-1 -> -0.01543682 | H47: -0.0154 | L47: weight of equity | M47: =1-M45 -> 0.99130143 | N47: =1-N45 -> 0.99059931 | O47: =1-O45 -> 0.90239734 | P47: =1-P45 -> 0.97873642
A48: 45311 | B48: 2290.1 | C48: =B48/B49-1 -> 0.0057090159 | D48: 0.0057 | E48: 45311 | F48: 21571.8 | G48: =F48/F49-1 -> -0.0023401658 | H48: -0.0023 | L48: weight of equity(%) | M48: =M47*100 -> 99.130143 | N48: =N47*100 -> 99.059931 | O48: =O47*100 -> 90.239734 | P48: =P47*100 -> 97.873642
A49: 45310 | B49: 2277.1 | C49: =B49/B50-1 -> 0.0075217911 | D49: 0.0075 | E49: 45310 | F49: 21622.4 | G49: =F49/F50-1 -> 0.007461939 | H49: 0.0075 | L49: WACC(%) | M49: #REF! | N49: #REF! | O49: #REF! | P49: =(P46*P43)+(P48*O4) -> -0.06250621
A50: 45309 | B50: 2260.1 | C50: =B50/B51-1 -> 0.0036859401 | D50: 0.0037 | E50: 45309 | F50: 21462.25 | G50: =F50/F51-1 -> -0.0050853075 | H50: -0.0051 | L50: WACC(%) | M50: 0.2796 | N50: 0.2785 | O50: 0.2517 | P50: -0.0625
A51: 45308 | B51: 2251.8 | C51: =B51/B52-1 -> -0.018588333 | D51: -0.0186 | E51: 45308 | F51: 21571.95 | G51: =F51/F52-1 -> -0.020894323 | H51: -0.0209 | L51: Average WACC | M51: =(M50+N50+O50+P50)/4 -> 0.186825
A52: 45307 | B52: 2294.45 | C52: =B52/B53-1 -> -0.011183417 | D52: -0.0112 | E52: 45307 | F52: 22032.3 | G52: =F52/F53-1 -> -0.002948304 | H52: -0.0029 | L52: Average WACC | M52: =ACC!$M$51 -> 0.186825
A53: 45306 | B53: 2320.4 | C53: =B53/B54-1 -> -0.0051449151 | D53: -0.0051 | E53: 45306 | F53: 22097.45 | G53: =F53/F54-1 -> 0.0092671464 | H53: 0.0093
A54: 45303 | B54: 2332.4 | C54: =B54/B55-1 -> 0.0045870572 | D54: 0.0046 | E54: 45303 | F54: 21894.55 | G54: =F54/F55-1 -> 0.01142642 | H54: 0.0114
A55: 45302 | B55: 2321.75 | C55: =B55/B56-1 -> 0.0065681089 | D55: 0.0066 | E55: 45302 | F55: 21647.2 | G55: =F55/F56-1 -> 0.0013183031 | H55: 0.0013
A56: 45301 | B56: 2306.6 | C56: =B56/B57-1 -> -0.0013205464 | D56: -0.0013 | E56: 45301 | F56: 21618.7 | G56: =F56/F57-1 -> 0.0034277333 | H56: 0.0034
A57: 45300 | B57: 2309.65 | C57: =B57/B58-1 -> -0.019152776 | D57: -0.0192 | E57: 45300 | F57: 21544.85 | G57: =F57/F58-1 -> 0.0014805002 | H57: 0.0015
A58: 45299 | B58: 2354.75 | C58: =B58/B59-1 -> -0.0095480452 | D58: -0.0095 | E58: 45299 | F58: 21513 | G58: =F58/F59-1 -> -0.009110673 | H58: -0.0091
A59: 45296 | B59: 2377.45 | C59: =B59/B60-1 -> 0.0081630057 | D59: 0.0082 | E59: 45296 | F59: 21710.8 | G59: =F59/F60-1 -> 0.0024101281 | H59: 0.0024
A60: 45295 | B60: 2358.2 | C60: =B60/B61-1 -> 0.034207526 | D60: 0.0342 | E60: 45295 | F60: 21658.6 | G60: =F60/F61-1 -> 0.0065644701 | H60: 0.0066
A61: 45294 | B61: 2280.2 | C61: =B61/B62-1 -> 0.0056895867 | D61: 0.0057 | E61: 45294 | F61: 21517.35 | G61: =F61/F62-1 -> -0.0068518125 | H61: -0.0069
A62: 45293 | B62: 2267.3 | C62: =B62/B63-1 -> 0.010698525 | D62: 0.0107 | E62: 45293 | F62: 21665.8 | G62: =F62/F63-1 -> -0.0035001541 | H62: -0.0035
A63: 45292 | B63: 2243.3 | C63: =B63/B64-1 -> 0.014494064 | D63: 0.0145 | E63: 45292 | F63: 21741.9 | G63: =F63/F64-1 -> 0.00048317182 | H63: 0.0005
A64: 45289 | B64: 2211.25 | C64: =B64/B65-1 -> 0.01868061 | D64: 0.0187 | E64: 45289 | F64: 21731.4 | G64: =F64/F65-1 -> -0.0021718468 | H64: -0.0022
... A117: 45211 | B117: 2029.55 | C117: =B117/B118-1 -> -0.0044881542 | D117: -0.0045 | E117: 45211 | F117: 19794 | G117: =F117/F118-1 -> -0.00087576061 | H117: -0.0009
A118: 45210 | B118: 2038.7 | C118: =B118/B119-1 -> 0.026406545 | D118: 0.0264 | E118: 45210 | F118: 19811.35 | G118: =F118/F119-1 -> 0.006170692 | H118: 0.0062 | L118: Variance of the stock | O118: Variance of the market
A119: 45209 | B119: 1986.25 | C119: =B119/B120-1 -> 0.01083997 | D119: 0.0108 | E119: 45209 | F119: 19689.85 | G119: =F119/F120-1 -> 0.0090968028 | H119: 0.0091 | L119: =_xlfn.VAR.P(C9:C750) -> 0.00034270302 | O119: =_xlfn.VAR.P(G8:G750) -> 7.4920996e-05
A120: 45208 | B120: 1964.95 | C120: =B120/B121-1 -> -0.022388617 | D120: -0.0224 | E120: 45208 | F120: 19512.35 | G120: =F120/F121-1 -> -0.0071819269 | H120: -0.0072 | L120: =L119-Q121 -> 0.00034270286 | M120: UNSYSTEMATIC RISK | Q120: systematic Risk
A121: 45205 | B121: 2009.95 | C121: =B121/B122-1 -> 0.0063587433 | D121: 0.0064 | E121: 45205 | F121: 19653.5 | G121: =F121/F122-1 -> 0.0055127074 | H121: 0.0055 | Q121: =O119*H9^2 -> 1.6857224e-10
A122: 45204 | B122: 1997.25 | C122: =B122/B123-1 -> -0.0046844243 | D122: -0.0047 | E122: 45204 | F122: 19545.75 | G122: =F122/F123-1 -> 0.0056415639 | H122: 0.0056
A123: 45203 | B123: 2006.65 | C123: =B123/B124-1 -> -0.013882746 | D123: -0.0139 | E123: 45203 | F123: 19436.1 | G123: =F123/F124-1 -> -0.0047442873 | H123: -0.0047
A124: 45202 | B124: 2034.9 | C124: =B124/B125-1 -> 0.011256057 | D124: 0.0113 | E124: 45202 | F124: 19528.75 | G124: =F124/F125-1 -> -0.0055783851 | H124: -0.0056
A125: 45198 | B125: 2012.25 | C125: =B125/B126-1 -> 0.0079645353 | D125: 0.008 | E125: 45198 | F125: 19638.3 | G125: =F125/F126-1 -> 0.0058775172 | H125: 0.0059
A126: 45197 | B126: 1996.35 | C126: =B126/B127-1 -> -0.011585592 | D126: -0.0116 | E126: 45197 | F126: 19523.55 | G126: =F126/F127-1 -> -0.0097837085 | H126: -0.0098
A127: 45196 | B127: 2019.75 | C127: =B127/B128-1 -> 0.0023324483 | D127: 0.0023 | E127: 45196 | F127: 19716.45 | G127: =F127/F128-1 -> 0.0026316191 | H127: 0.0026
A128: 45195 | B128: 2015.05 | C128: =B128/B129-1 -> 0.0074746263 | D128: 0.0075 | E128: 45195 | F128: 19664.7 | G128: =F128/F129-1 -> -0.00050064677 | H128: -0.0005
A129: 45194 | B129: 2000.1 | C129: =B129/B130-1 -> 0.010917362 | D129: 0.0109 | E129: 45194 | F129: 19674.55 | G129: =F129/F130-1 -> 1.5248358e-05 | H129: 0
A130: 45191 | B130: 1978.5 | C130: =B130/B131-1 -> -0.0076737887 | D130: -0.0077 | E130: 45191 | F130: 19674.25 | G130: =F130/F131-1 -> -0.0034494374 | H130: -0.0034
A131: 45190 | B131: 1993.8 | C131: =B131/B132-1 -> 0.0070714214 | D131: 0.0071 | E131: 45190 | F131: 19742.35 | G131: =F131/F132-1 -> -0.0079919001 | H131: -0.008
A132: 45189 | B132: 1979.8 | C132: =B132/B133-1 -> -0.013405093 | D132: -0.0134 | E132: 45189 | F132: 19901.4 | G132: =F132/F133-1 -> -0.011518231 | H132: -0.0115
A133: 45187 | B133: 2006.7 | C133: =B133/B134-1 -> -0.0099415349 | D133: -0.0099 | E133: 45187 | F133: 20133.3 | G133: =F133/F134-1 -> -0.0029243748 | H133: -0.0029
... A137: 45181 | B137: 2010.95 | C137: =B137/B138-1 -> -0.019550962 | D137: -0.0196 | E137: 45181 | F137: 19993.2 | G137: =F137/F138-1 -> -0.00015752875 | H137: -0.0002
A138: 45180 | B138: 2051.05 | C138: =B138/B139-1 -> 0.013239471 | D138: 0.0132 | E138: 45180 | F138: 19996.35 | G138: =F138/F139-1 -> 0.0089001234 | H138: 0.0089 | L138: Dividend Yield
A139: 45177 | B139: 2024.25 | C139: =B139/B140-1 -> -0.0085710787 | D139: -0.0086 | E139: 45177 | F139: 19819.95 | G139: =F139/F140-1 -> 0.0047092698 | H139: 0.0047 | L139: Financial Year | M139: price of the stock (Rs) | N139: Dividend (Rs) | O139: Dividend Yield
A140: 45176 | B140: 2041.75 | C140: =B140/B141-1 -> -0.00085637387 | D140: -0.0009 | E140: 45176 | F140: 19727.05 | G140: =F140/F141-1 -> 0.0059150326 | H140: 0.0059 | L140: 2022 | M140: 2119.45 | N140: 58 | O140: =ACC!$N140/ACC!$M140 -> 0.02736559
A141: 45175 | B141: 2043.5 | C141: =B141/B142-1 -> -0.019716013 | D141: -0.0197 | E141: 45175 | F141: 19611.05 | G141: =F141/F142-1 -> 0.0018467527 | H141: 0.0018 | L141: 2023 | M141: 1709 | N141: 0 | O141: =ACC!$N141/ACC!$M141 -> 0
A142: 45174 | B142: 2084.6 | C142: =B142/B143-1 -> 0.012605348 | D142: 0.0126 | E142: 45174 | F142: 19574.9 | G142: =F142/F143-1 -> 0.0023606161 | H142: 0.0024 | L142: 2024 | M142: 1791.5 | N142: 9.25 | O142: =ACC!$N142/ACC!$M142 -> 0.005163271
A143: 45173 | B143: 2058.65 | C143: =B143/B144-1 -> 0.023567433 | D143: 0.0236 | E143: 45173 | F143: 19528.8 | G143: =F143/F144-1 -> 0.0048108339 | H143: 0.0048 | N143: AVG | O143: =AVERAGE(O140:O142) -> 0.010842954
A144: 45170 | B144: 2011.25 | C144: =B144/B145-1 -> 0.0027421164 | D144: 0.0027 | E144: 45170 | F144: 19435.3 | G144: =F144/F145-1 -> 0.0094267106 | H144: 0.0094
A145: 45169 | B145: 2005.75 | C145: =B145/B146-1 -> 0.0025992852 | D145: 0.0026 | E145: 45169 | F145: 19253.8 | G145: =F145/F146-1 -> -0.0048404312 | H145: -0.0048
A146: 45168 | B146: 2000.55 | C146: =B146/B147-1 -> 0.009461096 | D146: 0.0095 | E146: 45168 | F146: 19347.45 | G146: =F146/F147-1 -> 0.00024815628 | H146: 0.0002
A147: 45167 | B147: 1981.8 | C147: =B147/B148-1 -> -0.0017378164 | D147: -0.0017 | E147: 45167 | F147: 19342.65 | G147: =F147/F148-1 -> 0.0018957788 | H147: 0.0019
A148: 45166 | B148: 1985.25 | C148: =B148/B149-1 -> 0.011566584 | D148: 0.0116 | E148: 45166 | F148: 19306.05 | G148: =F148/F149-1 -> 0.0020891943 | H148: 0.0021
A149: 45163 | B149: 1962.55 | C149: =B149/B150-1 -> -0.013967393 | D149: -0.014 | E149: 45163 | F149: 19265.8 | G149: =F149/F150-1 -> -0.0062362341 | H149: -0.0062
A150: 45162 | B150: 1990.35 | C150: =B150/B151-1 -> 0.012771912 | D150: 0.0128 | E150: 45162 | F150: 19386.7 | G150: =F150/F151-1 -> -0.0029469245 | H150: -0.0029
A151: 45161 | B151: 1965.25 | C151: =B151/B152-1 -> -0.0069981305 | D151: -0.007 | E151: 45161 | F151: 19444 | G151: =F151/F152-1 -> 0.0024514795 | H151: 0.0025
A152: 45160 | B152: 1979.1 | C152: =B152/B153-1 -> 0.0036258526 | D152: 0.0036 | E152: 45160 | F152: 19396.45 | G152: =F152/F153-1 -> 0.0001469557 | H152: 0.0001
A153: 45159 | B153: 1971.95 | C153: =B153/B154-1 -> 0.019569826 | D153: 0.0196 | E153: 45159 | F153: 19393.6 | G153: =F153/F154-1 -> 0.0043215615 | H153: 0.0043
A154: 45156 | B154: 1934.1 | C154: =B154/B155-1 -> 0.017492175 | D154: 0.0175 | E154: 45156 | F154: 19310.15 | G154: =F154/F155-1 -> -0.0028453028 | H154: -0.0028
A155: 45155 | B155: 1900.85 | C155: =B155/B156-1 -> 0.0045979441 | D155: 0.0046 | E155: 45155 | F155: 19365.25 | G155: =F155/F156-1 -> -0.0051245826 | H155: -0.0051
... A743: 44291 | B743: 1894.4 | C743: =B743/B744-1 -> -0.0099040949 | D743: -0.0099 | E743: 44291 | F743: 14637.8 | G743: =F743/F744-1 -> -0.015439873 | H743: -0.0154
A744: 44287 | B744: 1913.35 | D744: 0.0053 | E744: 44287 | F744: 14867.35 | H744: 0.012

Sheet PART 2
B2: Financial Data Summary (in ₹ Crores) | N2: Year | O2: Interest Coverage Ratio | Q2: Year | R2: Cash Flow Coverage Ratio
N3: 2022 | O3: 1.26 | Q3: 2022 | R3: 0.06
B4: Total Debt | C4: 4675 | D4: 4850 | E4: 4800 | N4: 2023 | O4: 0.93 | Q4: 2023 | R4: 0.04 | Y4: Year | Z4: Current Assets(₹ Cr) | AA4: Short-Term Liabilities (₹ Cr) | AB4: Long-Term Liabilities (₹ Cr) | AC4: Debt-to-Equity Ratio | AD4: Leverage Ratio (Current Liabilities/Current Assets) | AE4: Cash Reserves (₹ Cr) | AF4: Dividend Policy | AH4: Year | AI4: Cash Reserves (₹ Cr) | AJ4: Cash Flow from Operations (₹ Cr) | AK4: Interest Expense (₹ Cr) | AL4: Dividend (₹/Share)
B5: Shareholder's equity | C5: 3050 | D5: 3010 | E5: 2900 | N5: 2024 | O5: -1.39 | Q5: 2024 | R5: -0.04 | Y5: 2022 | Z5: 23986 | AA5: 22307 | AB5: 12165 | AC5: 0.79 | AD5: 0.93 | AE5: 688.4 | AF5: None | AH5: 2022 | AI5: 688.4 | AJ5: 270 | AK5: 210 | AL5: None | AS5: METRIC | AT5: FY 2022 | AU5: FY 2023 | AV5: FY 2024 | AY5: Metric | AZ5: FY 2022 | BA5: FY 2023 | BB5: FY 2024 | BC5: Interpretation | BG5: Metric | BH5: FY 2022 | BI5: FY 2023 | BJ5: FY 2024
B6: EBIT [Operating Income] | C6: 265 | D6: 185 | E6: -328 | Y6: 2023 | Z6: 32147 | AA6: 27968 | AB6: 14153 | AC6: 0.87 | AD6: 1 | AE6: 852.5 | AF6: None | AH6: 2023 | AI6: 852.5 | AJ6: 200 | AK6: 199 | AL6: None | AS6: Total Debt | AT6: 4675 | AU6: 4850 | AV6: 4800 | AY6: Interest Coverage Ratio | AZ6: 1.26 | BA6: 0.93 | BB6: -1.39 | BC6: Declining ability to cover interest payments | BF6: Focus on Debt Reduction | BG6: Total Debt (₹ crore) | BH6: 4675 | BI6: 4850 | BJ6: 4800
B7: Interest Expense | C7: 210 | D7: 199 | E7: 236 | Y7: 2024 | Z7: 34912 | AA7: 23042 | AB7: 12165 | AC7: 0.66 | AD7: 0.96 | AE7: 748.9 | AF7: None | AH7: 2024 | AI7: 748.9 | AJ7: -195 | AK7: 236 | AL7: None | AS7: Shareholder's equity | AT7: 3050 | AU7: 3010 | AV7: 2900 | AY7: Debt-to-Equity Ratio | AZ7: 1.53 | BA7: 1.61 | BB7: 1.66 | BC7: Increasing financial leverage | BG7: Interest Expense (₹ crore) | BH7: 210 | BI7: 199 | BJ7: 236
B8: Cashflow from Operations | C8: 270 | D8: 200 | E8: -195 | AS8: EBIT [Operating Income] | AT8: 265 | AU8: 185 | AV8: -328 | AY8: EBIT (₹ crore) | AZ8: 265 | BA8: 185 | BB8: -328 | BC8: Negative EBIT in FY 2024 limits dividend capacity | BG8: Debt-to-Equity Ratio | BH8: 1.53 | BI8: 1.61 | BJ8: 1.66
AS9: Interest Expense | AT9: 210 | AU9: 199 | AV9: 236 | AY9: Interest Expense (₹ crore) | AZ9: 210 | BA9: 199 | BB9: 236 | BC9: High fixed interest burden | BF9: Retention of Earnings | BG9: EBIT (₹ crore) | BH9: 265 | BI9: 185 | BJ9: -328
BG10: Shareholder Equity (₹ crore) | BH10: 3050 | BI10: 3010 | BJ10: 2900
M11: CRITERIA: | Q11: CRITERIA: | BF11: Stock Buybacks | BG11: Hypothetical Buyback (₹ crore) | BH11: 500 | BI11: - | BJ11: -
AE12: Leverage Ratios | BG12: Shares Bought Back (crore) | BH12: 2.5 | BI12: - | BJ12: -
BF13: Commitment to Dividends | BG13: Dividend Payout Foregone (₹ crore) | BH13: 200 | BI13: 200 | BJ13: 200
BG14: Debt Reduction Over 3 Years (₹ crore) | BH14: 600 | BI14: - | BJ14: -
BG15: Interest Savings (₹ crore) | BH15: 30 | BI15: - | BJ15: -
B16: Year | C16: Debt-to-Equity Ratio | BF16: Market Value Enhancement | BG16: Shareholder Equity (₹ crore) | BH16: 3050 | BI16: 3010 | BJ16: 2900
B17: 2022 | C17: 1.53 | BG17: Dividend Yield Foregone (%) | BH17: 2 | BI17: 2 | BJ17: 2
B18: 2023 | C18: 1.61
B19: 2024 | C19: 1.66
B26: Year | C26: Debt Proportion % | D26: Equity Proportion %
B27: FY 2022 | C27: 0.3263 | D27: 0.3404
B28: FY 2023 | C28: 0.3386 | D28: 0.3359
B29: FY 2024 | C29: 0.335 | D29: 0.3236
AI32: Analysis of Financing Needs
AD33: Cash Reserves | AI33: 1. Short-Term Liabilities vs. Current Assets (Leverage Ratio)
AI34: FY 2022 (0.93): Liquidity was manageable, with current assets covering short-term liabilities adequately.
N35: INTERPRETATION | AI35: FY 2023 (1.00): Liquidity hit its limit, as short-term liabilities equaled current assets, reflecting higher dependency on short-term financing.
M36: FY 2022 | N36: The company barely covers interest payments from operational earnings; weak cash flow to support debt. | AI36: FY 2024 (0.96): Slight improvement due to better working capital management, but cash reserves indicate ongoing challenges.
M37: FY 2023 | N37: Decline in EBIT leads to reduced capacity to meet interest; reliance on external funds increases. | AI37: 2. Long-Term Liabilities and Debt-to-Equity Ratio
M38: FY 2024 | N38: Negative EBIT and cash flow indicate inability to service debt, signaling high financial distress. | AI38: Long-term liabilities increased in FY 2023 (₹14,153 Cr) but stabilized in FY 2024 (₹12,165 Cr), suggesting cautious debt management.
AI39: Debt-to-equity ratio dropped from 0.87 (FY 2023) to 0.66 (FY 2024), showing improved financial stability, though equity erosion continues due to operational losses.
M40: INSIGHTS | AI40: 3. Cash Reserves and Cash Flow from Operations
M41: "India Cements Ltd. showed a declining trend in its ability to service debt, with operational challenges intensifying in 2024." | AI41: Cash reserves increased in FY 2023 (₹852.5 Cr) but dropped to ₹748.9 Cr in FY 2024, signaling reduced liquidity amidst negative cash flow (-₹195 Cr).
M42: "Urgent actions like cost reduction, revenue growth, or restructuring are critical to address financial distress." | AI42: Negative operating cash flow in FY 2024 reflects an inability to generate enough internal funds to meet financing needs.
AI43: 4. Interest Expense and Dividend | AY43: 1. High Debt Levels and Interest Obligations
AI44: Interest expense increased from ₹199 Cr in FY 2023 to ₹236 Cr in FY 2024, adding pressure on debt servicing. | AY44: Debt Dependency: Total debt remains consistently high, at ₹4,675 crore in FY 2022, ₹4,850 crore in FY 2023, and ₹4,800 crore in FY 2024.
AI45: Dividend payouts remained suspended over all three years, prioritizing cash conservation. | AY45: Interest Expense: The interest expense is significant, standing at ₹210 crore in FY 2022, ₹199 crore in FY 2023, and ₹236 crore in FY 2024, consuming a major portion of cash flows.
AY46: EBIT-Interest Coverage:
N47: Recommendations for Debt Servicing | AY47: FY 2022: EBIT of ₹265 crore barely covers interest expense (1.26x).
N48: Reduce Debt: Explore refinancing or asset sales to lower interest obligations. | AA48: Capital Structure Analysis | AI48: Key Insights on Financing Needs | AY48: FY 2023: EBIT of ₹185 crore fails to fully cover interest expense (0.93x).
N49: Increase EBIT: Focus on operational efficiency and revenue growth to return to positive ICR. | AY49: FY 2024: EBIT is negative (-₹328 crore), meaning the company cannot cover its interest obligations.
N50: Improve Cash Flow: Optimize working capital and reduce non-core expenses to stabilize CFCR. | AA50: Strengths | AI50: Debt Servicing: | AY50: Implication: High interest burdens prevent the company from paying dividends and prioritize debt servicing.
AA51: Moderate Debt Levels:
AA52: India Cements maintained a manageable debt-to-equity ratio across all years, below industry thresholds. | AI52: Rising interest expenses (₹236 Cr in FY 2024) and negative operating cash flows indicate challenges in meeting financing needs without external support. | AY52: 2. Profitability and Operational Challenges
AA53: Leverage Control: | AY53: Declining EBIT:
AA54: The leverage ratio remained under control, with short-term liabilities consistently backed by assets. | AI54: Liquidity Management: | AY54: EBIT has declined drastically from ₹265 crore in FY 2022 to ₹185 crore in FY 2023, turning negative (-₹328 crore) in FY 2024. | BO54: Metric | BP54: Formula | BQ54: Calculation
AY55: Negative Operating Income: A negative EBIT directly impacts net income, leaving no surplus for dividends. | BO55: Debt Reduction (3 Years) | BP55: Dividend Payout Foregone * 3 years | BQ55: ₹200 crore * 3 = ₹600 crore
AA56: Weaknesses | AI56: A leverage ratio close to 1 in FY 2023 and FY 2024 highlights reliance on short-term funding, with cash reserves insufficient to cover liabilities. | AY56: Implication: Weak profitability forces the company to forgo or significantly reduce dividends, with a focus on addressing operational inefficiencies. | BO56: Interest Savings Annually | BP56: Debt Reduction * Interest Rate (5%) | BQ56: ₹600 crore * 5% = ₹30 crore
AA57: Liquidity Challenges: | BO57: EBIT Recovery Target | BP57: Target EBIT - Current EBIT | BQ57: ₹265 crore - (-₹328 crore) = ₹593 crore
AA58: Although improving in 2024, leverage ratios close to 1 in 2023 highlight liquidity risks. | AI58: Capital Structure Adjustments: | AY58: 3. Shareholder's Equity Decline | BO58: Debt-to-Equity Ratio (FY 2024) | BP58: Total Debt / Shareholder Equity | BQ58: ₹4,800 crore / ₹2,900 crore = 1.66
AA59: Dividend Suspension: | AY59: Equity Erosion: Shareholder's equity has decreased steadily from ₹3,050 crore in FY 2022 to ₹2,900 crore in FY 2024. | BO59: Dividend Yield Foregone | BP59: Dividend Payout * Dividend Yield (2%) | BQ59: ₹200 crore * 2% = ₹4 crore
AA60: The absence of dividends reflects financial stress and prioritization of internal funding. | AI60: Reduction in debt-to-equity ratio in FY 2024 suggests improved financial discipline and reduced risk exposure, albeit with operational setbacks. | AY60: Implication: A declining equity base signals deteriorating financial health, limiting the ability to pay dividends without further weakening shareholder value. | BO60: Shares Repurchased | BP60: Total Buyback / Buyback Price per Share | BQ60: ₹500 crore / ₹200 = 2.5 crore shares
AA62: Key Risks
AA63: Declining Cash Reserves: A significant drop from 2023 to 2024 indicates reliance on external financing or reduced operating efficiency. | AY63: 4. Capital Allocation Priority
AA64: Dependence on Debt: Though the debt-to-equity ratio improved in 2024, consistent focus on reducing liabilities is critical. | AY64: Debt Servicing Focus: High debt levels and rising interest expenses are likely prompting the company to allocate cash flow to service debt rather than distribute dividends. | BO64: 1. Debt Reduction and Interest Savings
AY65: Operational Turnaround: Funds are likely redirected toward stabilizing operations and addressing the EBIT decline. | BO65: Formula for Debt Reduction (3 years)
AA66: 3. Recommendations | AY66: Implication: Dividend policy is expected to remain conservative or suspended until the debt and operational issues are resolved. | BO66: Debt Reduction Target: ₹600 crore over 3 years.
AA67: Focus on Operational Efficiency:
AA68: Increase EBIT through cost-cutting and operational improvements to stabilize financial performance. | AY68: 5. Market Signals and Shareholder Expectations | BO68: Interest savings per year from debt reduction (assuming 5% interest rate)
AA69: Improve Liquidity: | AY69: Short-Term Impact: Shareholders might view dividend cuts as a disappointment, but paying dividends under the current scenario could indicate poor financial management.
AA70: Build cash reserves and reduce reliance on debt to enhance financial flexibility. | AY70: Long-Term Strategy: The company could justify dividend suspension by focusing on debt reduction and profitability recovery. | BO70: 2. EBIT and Operational Recovery
AA71: Gradual Dividend Reinstatement: | AY71: Likely Dividend Policy: | BO71: Formula for EBIT Recovery Target
AA72: Reassess dividend policy once cash flows stabilize to regain investor confidence. | AY72: Suspension of dividends due to negative EBIT and high debt. | BO72: Target to return EBIT to ₹265 crore (FY 2022 level) from -₹328 crore (FY 2024):
AY73: Minimal or token dividends, if any, to maintain shareholder goodwill.
AY74: Focus on retaining earnings for debt servicing and operational improvements. | BO74: Debt-to-Equity Ratio = Total Debt / Shareholder Equity
BO76: Hypothetical Dividend Yield: 2% of dividend payout (₹200 crore).
BO78: If ₹500 crore is allocated for buyback at ₹200 per share:
BO81: EPS increase after buyback (assuming current EPS is ₹10 per share)
BO84: EPS Increase = (Net Income / New Shares Outstanding) - Current EPS
BO85: New Shares Outstanding = Original Shares - Shares Repurchased
BO86: =(Shares Outstanding - 2.5 crore) -> #ERROR!
BO87: EPS Increase would depend on specific share count and net income, which are not provided but can be calculated once the data is known.

Sheet PART 3
A1: India Cements | M1: Is the company capable of handling its financial obligations without facing difficulties?
B2: Rev | C2: Rev Growth | D2: NI | E2: NI Growth | G2: EPS(in Rs.) | H2: Current Assets | I2: Current Liabilities | J2: Current Ratio | L2: QUESTION NO.
A3: 2020 | B3: 5058 | D3: -36 | L3: 1)
A4: 2021 | B4: 4437 | C4: =(B4-B3)/B3 -> -0.1227758 | D4: 222 | E4: =(D4-D3)/ABS(D3) -> 7.1666667 | G4: 7.16 | H4: 1650 | I4: 2537 | J4: =H4/I4 -> 0.65037446
A5: 2022 | B5: 4713 | C5: =(B5-B4)/B4 -> 0.062204192 | D5: 39 | E5: =(D5-D4)/ABS(D4) -> -0.82432432 | G5: 1.26 | H5: 2381 | I5: 2689 | J5: =H5/I5 -> 0.88545928 | M5: Following ratios here depict:
A6: 2023 | B6: 5381 | C6: =(B6-B5)/B5 -> 0.14173562 | D6: -189 | E6: =(D6-D5)/ABS(D5) -> -5.8461538 | G6: -6.08 | H6: 3198 | I6: 2775 | J6: =H6/I6 -> 1.1524324 | M6: 1. Current Ratio - Current Ratio here measures whether company can meet it's short term obligations using its short term assets.
B7: Avg Rev Growth | C7: =AVERAGE(C4:C6) -> 0.027054672 | D7: Average NI Growth | E7: =AVERAGE(E4:E6) -> 0.16539617 | F7: Average EPS | G7: =AVERAGE(G4:G6) -> 0.78 | I7: Average CR | J7: =AVERAGE(J4:J6) -> 0.89608872 | M7: 2. D/E Ratio -D/E Ratio here measures the proportion of Debt financing relative to Equity financing
B8: Avg Rev Growth of industry | C8: =AVERAGE($C$7,$C$18,$C$29,$C$40) -> 0.12894596 | D8: Average NI Growth of Industry | E8: =AVERAGE($E$7,$E$18,$E$29,$E$40) -> 0.1669909 | F8: Industry Average EPS | G8: =AVERAGE($G$7,$G$18,$G$29,$G$40) -> 79.259167 | I8: Industry Average CR | J8: =AVERAGE($J$7,$J$18,$J$29,$J$40) -> 1.3119324 | M8: 3. Interest Coverage Ratio - Interest Coverage Ratio here depicts the ability to cover interest payments with operating income.
M11: Last 3 years average | N11: Current Ratio | O11: D/E Ratio | P11: Interest Coverage Ratio
A12: Ultra Tech | M12: India Cements | N12: 0.8961 | O12: 9.06 | P12: 0.93
B13: Rev | C13: Rev Growth | D13: NI | E13: NI Growth | G13: EPS(in Rs.) | H13: Current Assets | I13: Current Liabilities | J13: Current Ratio | M13: Industry Average | N13: 1.265 | O13: 9.21 | P13: 15.44
A14: 2020 | B14: 42430 | D14: 5751
A15: 2021 | B15: 44726 | C15: =(B15-B14)/B14 -> 0.054112656 | D15: 5462 | E15: =(D15-D14)/ABS(D14) -> -0.05025213 | G15: 199.4 | H15: 22992 | I15: 19587.76 | J15: =H15/I15 -> 1.1737942
A16: 2022 | B16: 52599 | C16: =(B16-B15)/B15 -> 0.17602737 | D16: 7334 | E16: =(D16-D15)/ABS(D15) -> 0.3427316 | G16: 189.26 | H16: 18991 | I16: 19172 | J16: =H16/I16 -> 0.99055915 | N16: INDIA CEMENTS | O16: INDUSTRY AVG
A17: 2023 | B17: 63240 | C17: =(B17-B16)/B16 -> 0.20230423 | D17: 5073 | E17: =(D17-D16)/ABS(D16) -> -0.30829016 | G17: 254.42 | H17: 21864 | I17: 22248 | J17: =H17/I17 -> 0.98274002 | M17: 2021 | N17: 0.6504 | O17: 1.2069
B18: Avg Rev Growth | C18: =AVERAGE(C15:C17) -> 0.14414808 | D18: Average NI Growth | E18: =AVERAGE(E15:E17) -> -0.0052702285 | F18: Average EPS | G18: =AVERAGE(G15:G17) -> 214.36 | I18: Average CR | J18: =AVERAGE(J15:J17) -> 1.0490311 | M18: 2022 | N18: 0.8855 | O18: 1.3966
B19: Avg Rev Growth of industry | C19: =AVERAGE($C$7,$C$18,$C$29,$C$40) -> 0.12894596 | D19: Average NI Growth of Industry | E19: =AVERAGE($E$7,$E$18,$E$29,$E$40) -> 0.1669909 | F19: Industry Average EPS | G19: =AVERAGE($G$7,$G$18,$G$29,$G$40) -> 79.259167 | I19: Industry Average CR | J19: =AVERAGE($J$7,$J$18,$J$29,$J$40) -> 1.3119324 | M19: 2023 | N19: 1.1524 | O19: 1.3323
A23: Ambuja
B24: Rev | C24: Rev Growth | D24: NI | E24: NI Growth | G24: EPS(in Rs.) | H24: Current Assets | I24: Current Liabilities | J24: Current Ratio
A25: 2020 | B25: 11743.86 | D25: 1790.1
A26: 2021 | B26: 14250.59 | C26: =(B26-B25)/B25 -> 0.21345026 | D26: 2080.54 | E26: =(D26-D25)/D25 -> 0.16224792 | G26: 10.33 | H26: 6774 | I26: 5357 | J26: =H26/I26 -> 1.2645137
A27: 2022 | B27: 20937.7 | C27: =(B27-B26)/B26 -> 0.46925145 | D27: 2553.49 | E27: =(D27-D26)/D26 -> 0.22732079 | G27: 12.86 | H27: 10876 | I27: 5436 | J27: =H27/I27 -> 2.0007358
A28: 2023 | B28: 18771.97 | C28: =(B28-B27)/B27 -> -0.10343686 | D28: 2334.69 | E28: =(D28-D27)/D27 -> -0.085686648 | G28: 11.74 | H28: 11246 | I28: 6423 | J28: =H28/I28 -> 1.7508952
B29: Avg Rev Growth | C29: =AVERAGE(C26:C28) -> 0.19308828 | D29: Average NI Growth | E29: =AVERAGE(E26:E28) -> 0.10129402 | F29: Average EPS | G29: =AVERAGE(G26:G28) -> 11.643333 | I29: Average CR | J29: =AVERAGE(J26:J28) -> 1.6720483
B30: Avg Rev Growth of industry | C30: =AVERAGE($C$7,$C$18,$C$29,$C$40) -> 0.12894596 | D30: Average NI Growth of Industry | E30: =AVERAGE($E$7,$E$18,$E$29,$E$40) -> 0.1669909 | F30: Industry Average EPS | G30: =AVERAGE($G$7,$G$18,$G$29,$G$40) -> 79.259167 | I30: Industry Average CR | J30: =AVERAGE($J$7,$J$18,$J$29,$J$40) -> 1.3119324
A34: ACC
B35: Rev | C35: Rev Growth | D35: NI | E35: NI Growth | G35: EPS(in Rs.) | H35: Current Assets | I35: Current Liabilities | J35: Current Ratio
A36: 2020 | B36: 13988.52 | D36: 1400.4
A37: 2021 | B37: 16356.11 | C37: =(B37-B36)/B36 -> 0.16925236 | D37: 1820.27 | E37: =(D37-D36)/D36 -> 0.29982148 | G37: 99.21 | H37: 8330 | I37: 4790 | J37: =H37/I37 -> 1.7390397
A38: 2022 | B38: 22547.15 | C38: =(B38-B37)/B37 -> 0.37851543 | D38: 869.91 | E38: =(D38-D37)/D37 -> -0.52209837 | G38: 47.13 | H38: 10246 | I38: 5993 | J38: =H38/I38 -> 1.7096613
A39: 2023 | B39: 20443.74 | C39: =(B39-B38)/B38 -> -0.093289396 | D39: 2124.24 | E39: =(D39-D38)/D38 -> 1.4419078 | G39: 124.42 | H39: 8124 | I39: 5630 | J39: =H39/I39 -> 1.442984
B40: Avg Rev Growth | C40: =AVERAGE(C37:C39) -> 0.1514928 | D40: Average NI Growth | E40: =AVERAGE(E37:E39) -> 0.40654363 | F40: Average EPS | G40: =AVERAGE(G37:G39) -> 90.253333 | I40: Average CR | J40: =AVERAGE(J37:J39) -> 1.6305617
B41: Avg Rev Growth of industry | C41: =AVERAGE($C$7,$C$18,$C$29,$C$40) -> 0.12894596 | D41: Average NI Growth of Industry | E41: =AVERAGE($E$7,$E$18,$E$29,$E$40) -> 0.1669909 | F41: Industry Average EPS | G41: =AVERAGE($G$7,$G$18,$G$29,$G$40) -> 79.259167 | I41: Industry Average CR | J41: =AVERAGE($J$7,$J$18,$J$29,$J$40) -> 1.3119324
A44: Last 3 Year Average | B44: Standard Deviation
A45: India Cements | B45: 0.424299
A46: Ultra Tech | B46: 0.227696
A47: Ambuja | B47: 0.344584
A48: ACC | B48: 0.290393
A49: Industry Average | B49: =AVERAGE(B45:B48) -> 0.321743
L50: Ranking- | M50: 2
L51: Analysis- | M51: A low Current Ratio indicates weak liquidity, limiting the company's ability to manage short-term obligations effectively.
A52: Industry Average | M52: The very low Interest Coverage Ratio reflects poor solvency, while the high D/E Ratio although slightly better than industry peers, remains significantly high at 9, underscoring substantial financial risk.
B53: Rev Growth | C53: NI Growth | D53: EPS(in Rs.) | E53: Current Ratio
A54: 2021 | B54: =AVERAGE(C4,C15,C26,C37) -> 0.078509869 | C54: =AVERAGE(E4,E15,E26,E37) -> 1.894621 | D54: =AVERAGE(G4,G15,G26,G37) -> 79.025 | E54: =AVERAGE(J4,J15,J26,J37) -> 1.2069305
A55: 2022 | B55: =AVERAGE(C5,C16,C27,C38) -> 0.27149961 | C55: =AVERAGE(E5,E16,E27,E38) -> -0.19409258 | D55: =AVERAGE(G5,G16,G27,G38) -> 62.6275 | E55: =AVERAGE(J5,J16,J27,J38) -> 1.3966039
A56: 2023 | B56: =AVERAGE(C6,C17,C28,C39) -> 0.036828398 | C56: =AVERAGE(E6,E17,E28,E39) -> -1.1995557 | D56: =AVERAGE(G6,G17,G28,G39) -> 96.125 | E56: =AVERAGE(J6,J17,J28,J39) -> 1.3322629
M57: Does the company consistently provide returns to its shareholders compared to its industry peers?
L58: 2)
M60: Following ratios here depict:
M61: 1. Dividend Yield - Dividend Yield here measures how much dividend is generated reltaive to share price.
M62: 2. EPS - Earning Per Share here measures the profitability on a per share basis
M65: Last 3 years average | N65: Div Yield | O65: EPS(In INR)
M66: India Cements | N66: 0.0026 | O66: 0.78
M67: Industry Average | N67: 0.0066 | O67: 79.26
L86: Ranking- | M86: 1.5
L87: Analysis- | M87: The company's poor Dividend Yield and exceptionally low EPS indicate its inability to generate substantial profits or consistent income.
L93: 3) | M93: Does the company demonstrate stability in its stock price, showing lower volatility than the overall market?
M95: Following ratios here depict:
M96: Beta- Beta here measures company's relative risk with respect to industry
M99: Last 3 years average | N99: Beta | O99: Std Dev.
M100: India Cements | N100: 1.499 | O100: 0.424299
M101: Industry Average | N101: 1.12175 | O101: 0.321743
L120: Ranking- | M120: 2.5
L121: Analysis- | M121: The company’s higher Beta and Standard Deviation show that it is more volatile and faces greater financial risk, which makes it harder to manage its financial obligations smoothly.
M122: This higher level of risk suggests the company could have trouble staying stable in uncertain economic times.
L127: 4) | M127: Does the company show promising signs of growth in revenue and earnings, indicating strong future potential?
M131: Last 3 years average | N131: Rev Growth | O131: Net Income Growth
M132: India Cements | N132: 0.027055 | O132: 0.165396
M133: Industry Average | N133: 0.128946 | O133: 0.166991
L154: Ranking- | M154: 2.5
L155: Analysis- | M155: Revenue Growth is extremely low when compared with Industry Average which shows that the company is not performing well but the
M156: net income growth of India Cements is similar to its peers which depicts the expenses are not much higher relatively when we compare to its peer.
L163: 5) | M163: Does the company’s commitment to environmental and social initiatives positively impact its long-term sustainability?
L209: Ranking- | M209: 3.5
L210: Analysis- | M210: The company’s environmental and social initiatives have tangibly reduced its environmental impact and strengthened community ties, ensuring long-term sustainability.
M211: Its proactive measures reflect a clear alignment with global sustainability goals and industry best practices.
M212: Through overall analysis it can be concluded that the companny has performed well but other companies in this sector has outperformed it(ESG rank 100/130),
M213: and basically were more relatively environmentally conscious.
